{
  "algorithm_name": "E3HybridRouter",
  "scenario_name": "Single Road Closure Scenario",
  "seed": 9,
  "config_details": {
    "name": "Single Road Closure Scenario",
    "simulation": {
      "dt": 1.0,
      "max_steps": 600,
      "mode": "sumo",
      "network_file_path": "data/networks/midtown_manhattan.net.xml",
      "osm_file": null,
      "network_file": "data/networks/midtown_manhattan.net.xml",
      "route_file": null,
      "scenario_file": "data/scenarios/manhattan.yaml",
      "output_dir": "outputs",
      "sumo_binary": "sumo",
      "use_gui": false,
      "step_length": 1.0,
      "seed": 9,
      "traci_port": 8891,
      "output_directory": "outputs",
      "enable_subscriptions": true,
      "real_time_factor": -1.0,
      "breakdown_probability": 0.0
    },
    "battery": {
      "capacity_kwh": 60.0,
      "mass_kg": 1500.0,
      "efficiency": 0.9,
      "drag_coeff": 0.25,
      "frontal_area": 2.2,
      "rolling_res_coeff": 0.01,
      "regen_efficiency": 0.7
    },
    "charging_stations": [
      {
        "id": "station_west",
        "node_id": "42432825",
        "capacity": 4,
        "power_kw": 150.0,
        "base_price_per_kwh": 0.35
      },
      {
        "id": "station_east",
        "node_id": "42437644",
        "capacity": 4,
        "power_kw": 150.0,
        "base_price_per_kwh": 0.35
      }
    ],
    "communication": {
      "v2v_range_m": 150.0,
      "v2i_range_m": 300.0,
      "base_packet_loss_rate": 0.05,
      "base_latency_s": 0.002,
      "latency_jitter_s": 0.001,
      "propagation_speed_m_s": 300000000.0,
      "blackout_start_time": null,
      "blackout_end_time": null,
      "blackout_area": null
    },
    "emergencies": [],
    "infrastructure_failures": [],
    "ambulance_dispatches": [],
    "road_closures": [
      {
        "id": "closure_broadway",
        "start_time": 100.0,
        "duration": 800.0,
        "edge_id": "-1088325196#1"
      }
    ],
    "algorithms": {
      "objectives": {
        "w_time": 0.33,
        "w_distance": 0.0,
        "w_energy": 0.33,
        "w_congestion": 0.0,
        "w_emergency": 0.34
      },
      "aco": {
        "num_ants": 5,
        "max_iterations": 5,
        "alpha": 1.0,
        "beta": 2.0,
        "q_zero": 0.9,
        "evaporation_rate": 0.1,
        "local_evaporation_rate": 0.1,
        "q": 1.0,
        "initial_pheromone": 0.1,
        "min_pheromone": 1e-06,
        "max_pheromone": 10.0,
        "evaporation_dt": 1.0,
        "collect_metrics": false
      },
      "bco": {
        "colony_size": 5,
        "max_iterations": 5,
        "scout_ratio": 0.2,
        "recruitment_factor": 0.5,
        "abandonment_threshold": 0.2,
        "elite_route_seeding": false,
        "collect_metrics": false
      },
      "pso": {
        "swarm_size": 5,
        "max_iterations": 5,
        "inertia_weight": 0.7,
        "cognitive_weight": 1.5,
        "social_weight": 1.5,
        "v_max": 5.0,
        "collect_metrics": false
      },
      "e3_hybrid": {
        "max_iterations": 15,
        "collect_metrics": true,
        "share_aco_to_pso": true,
        "share_gbest_to_pso": true,
        "share_gbest_to_bco": true,
        "share_bco_pso_to_aco": true,
        "disable_aco": false,
        "disable_bco": false,
        "disable_pso": false,
        "disable_elite_sharing": false,
        "enable_adaptive_weighting": false
      }
    }
  },
  "timestamp": "2026-07-15T10:01:32.630218",
  "ablation_settings": {
    "share_aco_to_pso": true,
    "share_gbest_to_pso": true,
    "share_gbest_to_bco": true,
    "share_bco_pso_to_aco": true
  },
  "cpu_utilization_percent": 0.0,
  "memory_usage_mb": 0.0,
  "vehicle_travel_times": {
    "v_40": 0.0,
    "v_51": 0.0,
    "v_54": 0.0,
    "v_57": 0.0,
    "v_64": 0.0,
    "v_68": 0.0,
    "v_73": 0.0,
    "v_78": 0.0,
    "v_79": 0.0,
    "v_105": 0.0,
    "v_107": 0.0,
    "v_122": 0.0,
    "v_126": 0.0,
    "v_144": 0.0,
    "v_149": 0.0,
    "v_156": 0.0,
    "v_158": 0.0,
    "v_164": 0.0,
    "v_165": 0.0,
    "v_169": 0.0,
    "v_171": 0.0,
    "v_175": 0.0,
    "v_179": 0.0,
    "v_180": 0.0,
    "v_182": 0.0,
    "v_184": 0.0,
    "v_186": 0.0,
    "v_193": 0.0,
    "v_196": 0.0,
    "v_198": 0.0,
    "v_199": 0.0,
    "v_4": 23.0,
    "v_30": 54.0,
    "v_120": 54.0,
    "v_192": 57.0,
    "v_20": 60.0,
    "v_140": 61.0,
    "v_163": 65.0,
    "v_25": 77.0,
    "v_63": 84.0,
    "v_6": 86.0,
    "v_59": 92.0,
    "v_160": 96.0,
    "v_151": 99.0,
    "v_129": 110.0,
    "v_3": 111.0,
    "v_114": 111.0,
    "v_65": 121.0,
    "v_154": 131.0,
    "v_49": 136.0,
    "v_93": 0.0,
    "v_44": 139.0,
    "v_134": 143.0,
    "v_34": 144.0,
    "v_100": 155.0,
    "v_170": 155.0,
    "v_142": 161.0,
    "v_77": 163.0,
    "v_35": 164.0,
    "v_91": 180.0,
    "v_16": 188.0,
    "v_146": 188.0,
    "v_133": 190.0,
    "v_190": 196.0,
    "v_1": 197.0,
    "v_115": 198.0,
    "v_89": 199.0,
    "v_80": 211.0,
    "v_26": 220.0,
    "v_172": 233.0,
    "v_67": 234.0,
    "v_43": 235.0,
    "v_188": 235.0,
    "v_36": 236.0,
    "v_189": 246.0,
    "v_181": 247.0,
    "v_48": 249.0,
    "v_127": 250.0,
    "v_37": 251.0,
    "v_197": 253.0,
    "v_173": 279.0,
    "v_191": 279.0,
    "v_41": 280.0,
    "v_53": 280.0,
    "v_161": 281.0,
    "v_185": 285.0,
    "v_45": 287.0,
    "v_32": 294.0,
    "v_88": 294.0,
    "v_95": 300.0,
    "v_103": 323.0,
    "v_31": 324.0,
    "v_166": 324.0,
    "v_42": 325.0,
    "v_152": 328.0,
    "v_66": 329.0,
    "v_138": 329.0,
    "v_98": 334.0,
    "v_104": 341.0,
    "v_112": 348.0,
    "v_69": 352.0,
    "v_62": 353.0,
    "v_84": 356.0,
    "v_56": 366.0,
    "v_61": 368.0,
    "v_159": 368.0,
    "v_13": 369.0,
    "v_81": 369.0,
    "v_99": 369.0,
    "v_102": 369.0,
    "v_168": 369.0,
    "v_47": 371.0,
    "v_76": 371.0,
    "v_75": 373.0,
    "v_113": 374.0,
    "v_110": 376.0,
    "v_135": 378.0,
    "v_74": 383.0,
    "v_86": 392.0,
    "v_15": 394.0,
    "v_14": 398.0,
    "v_46": 401.0,
    "v_55": 415.0,
    "v_125": 415.0,
    "v_12": 416.0,
    "v_123": 423.0,
    "v_87": 434.0,
    "v_21": 453.0,
    "v_9": 454.0,
    "v_118": 458.0,
    "v_148": 458.0,
    "v_128": 459.0,
    "v_176": 460.0,
    "v_52": 462.0,
    "v_183": 462.0,
    "v_0": 467.0,
    "v_157": 467.0,
    "v_28": 469.0,
    "v_92": 472.0,
    "v_150": 486.0,
    "v_108": 491.0,
    "v_38": 500.0,
    "v_10": 501.0,
    "v_72": 504.0,
    "v_29": 505.0,
    "v_58": 510.0,
    "v_162": 510.0,
    "v_143": 514.0,
    "v_60": 521.0,
    "v_83": 521.0,
    "v_145": 543.0,
    "v_27": 555.0,
    "v_139": 557.0,
    "v_177": 557.0,
    "v_50": 558.0,
    "v_33": 564.0,
    "v_101": 566.0,
    "v_90": 577.0,
    "v_117": 580.0,
    "v_119": 585.0,
    "v_111": 593.0,
    "v_19": 594.0,
    "v_153": 594.0,
    "v_109": 595.0
  },
  "vehicle_free_flow_times": {
    "v_40": 81.35017019747544,
    "v_51": 103.91281104893312,
    "v_54": 103.87170085427157,
    "v_57": 62.41603977585193,
    "v_64": 155.98611953619738,
    "v_68": 84.39157779820916,
    "v_73": 147.53077206417402,
    "v_78": 183.96740682927836,
    "v_79": 187.98666057433664,
    "v_105": 95.84018630924554,
    "v_107": 220.885538817002,
    "v_122": 88.44713558756536,
    "v_126": 73.39083342026734,
    "v_144": 163.99578080265206,
    "v_149": 1413.6884023940627,
    "v_156": 248.08313294920953,
    "v_158": 239.92444146507634,
    "v_164": 126.62090395916806,
    "v_165": 387.41874181371384,
    "v_169": 151.20444110446118,
    "v_171": 46.31332820744644,
    "v_175": 184.53077945885929,
    "v_179": 175.13191753246508,
    "v_180": 206.4904430543589,
    "v_182": 222.96095505627716,
    "v_184": 129.07066189624328,
    "v_186": 656.0546640877512,
    "v_193": 196.4722719141324,
    "v_196": 115.42754919499106,
    "v_198": 184.48687103242835,
    "v_199": 312.6346363131736,
    "v_4": 13.986416383107432,
    "v_30": 23.84969238239116,
    "v_120": 13.646062549009821,
    "v_192": 37.063086402103934,
    "v_20": 30.561195104391647,
    "v_140": 39.10240375760994,
    "v_163": 45.08666161805446,
    "v_25": 34.65929079877545,
    "v_63": 54.70125223613596,
    "v_6": 56.03398926654741,
    "v_59": 57.76296894459534,
    "v_160": 89.22625960942801,
    "v_151": 62.12213262652762,
    "v_129": 29.735421166306693,
    "v_3": 65.52857037984367,
    "v_114": 80.36714873185817,
    "v_65": 108.20690422594643,
    "v_154": 57.05456171735241,
    "v_49": 57.94828134679458,
    "v_93": 120.76759190212906,
    "v_44": 61.57895633758309,
    "v_134": 87.18779935887777,
    "v_34": 64.45570679927,
    "v_100": 64.94322951480518,
    "v_170": 72.82479291021326,
    "v_142": 67.63559644059856,
    "v_77": 102.57602862254024,
    "v_35": 94.77681527874908,
    "v_91": 140.73613595706618,
    "v_16": 92.20866094576478,
    "v_146": 87.42397137745975,
    "v_133": 48.365213645162406,
    "v_190": 72.77297472731698,
    "v_1": 65.3911663453328,
    "v_115": 77.18425760286226,
    "v_89": 67.19745740555425,
    "v_80": 114.60644007155635,
    "v_26": 131.86769609415148,
    "v_172": 109.88898835404895,
    "v_67": 110.62042292430557,
    "v_43": 127.7268134112777,
    "v_188": 87.04788711715227,
    "v_36": 88.9622918896363,
    "v_189": 107.81438944633983,
    "v_181": 114.6824246274761,
    "v_48": 138.31617706719422,
    "v_127": 132.32826475849734,
    "v_37": 120.41896075863127,
    "v_197": 121.88063039764336,
    "v_173": 96.44940054169548,
    "v_191": 108.99105545617175,
    "v_41": 103.02420951225511,
    "v_53": 74.99642218246869,
    "v_161": 77.55992844364937,
    "v_185": 167.85688729874778,
    "v_45": 118.38461538461537,
    "v_32": 151.55419079890424,
    "v_88": 127.63886645776746,
    "v_95": 121.2998315412048,
    "v_103": 83.27554282240605,
    "v_31": 126.19518424214792,
    "v_166": 140.8951749691867,
    "v_42": 89.18429108855548,
    "v_152": 172.3944543828265,
    "v_66": 133.51312703570477,
    "v_138": 176.5587751190996,
    "v_98": 105.23455182619378,
    "v_104": 142.2559768742651,
    "v_112": 148.13328336237572,
    "v_69": 166.53007272834986,
    "v_62": 161.64394791171628,
    "v_84": 94.04229951407108,
    "v_56": 175.32225598988032,
    "v_61": 142.07083898404406,
    "v_159": 72.75301339041356,
    "v_13": 145.61559712074555,
    "v_81": 124.40810688633282,
    "v_99": 149.55392999687035,
    "v_102": 130.72267406442907,
    "v_168": 125.64830491557099,
    "v_47": 110.28201320230546,
    "v_76": 148.5162612174242,
    "v_75": 110.41844623807556,
    "v_113": 127.50383990747645,
    "v_110": 169.6044425211636,
    "v_135": 80.72957018536907,
    "v_74": 139.52728246856532,
    "v_86": 225.08874509898405,
    "v_15": 115.99145470866803,
    "v_14": 183.24505538662456,
    "v_46": 181.06809766488809,
    "v_55": 150.4808539109358,
    "v_125": 125.42583305321264,
    "v_12": 130.19586490325855,
    "v_123": 121.19480749489261,
    "v_87": 161.19845360492803,
    "v_21": 209.29087411826373,
    "v_9": 136.6883158113004,
    "v_118": 220.82684676817988,
    "v_148": 147.4542160419653,
    "v_128": 124.10122918252408,
    "v_176": 148.61367748898516,
    "v_52": 195.741935950174,
    "v_183": 211.986839478602,
    "v_0": 220.31128944389283,
    "v_157": 162.0152855750073,
    "v_28": 180.27632985159948,
    "v_92": 191.75021540316135,
    "v_150": 164.80155025880575,
    "v_108": 210.87141107423392,
    "v_38": 179.7796570202077,
    "v_10": 238.43711947325139,
    "v_72": 101.40093213256924,
    "v_29": 136.30149230279827,
    "v_58": 300.2015574711089,
    "v_162": 117.93866515723464,
    "v_143": 144.4734604858346,
    "v_60": 146.402162624483,
    "v_83": 210.37355351464555,
    "v_145": 278.28091312719476,
    "v_27": 163.2097402154161,
    "v_139": 221.4496896777775,
    "v_177": 283.61774649340435,
    "v_50": 217.9994948059965,
    "v_33": 217.46235359700958,
    "v_101": 309.0148695796644,
    "v_90": 220.98786079224578,
    "v_117": 175.62639028211197,
    "v_119": 244.41687700173864,
    "v_111": 107.72334571016071,
    "v_19": 208.91368354216812,
    "v_153": 295.1255987544912,
    "v_109": 227.13346302599905
  },
  "vehicle_delays": {
    "v_40": 0.0,
    "v_51": 0.0,
    "v_54": 0.0,
    "v_57": 0.0,
    "v_64": 0.0,
    "v_68": 0.0,
    "v_73": 0.0,
    "v_78": 0.0,
    "v_79": 0.0,
    "v_105": 0.0,
    "v_107": 0.0,
    "v_122": 0.0,
    "v_126": 0.0,
    "v_144": 0.0,
    "v_149": 0.0,
    "v_156": 0.0,
    "v_158": 0.0,
    "v_164": 0.0,
    "v_165": 0.0,
    "v_169": 0.0,
    "v_171": 0.0,
    "v_175": 0.0,
    "v_179": 0.0,
    "v_180": 0.0,
    "v_182": 0.0,
    "v_184": 0.0,
    "v_186": 0.0,
    "v_193": 0.0,
    "v_196": 0.0,
    "v_198": 0.0,
    "v_199": 0.0,
    "v_4": 9.013583616892568,
    "v_30": 30.15030761760884,
    "v_120": 40.35393745099018,
    "v_192": 19.936913597896066,
    "v_20": 29.438804895608353,
    "v_140": 21.89759624239006,
    "v_163": 19.913338381945543,
    "v_25": 42.34070920122455,
    "v_63": 29.298747763864043,
    "v_6": 29.966010733452592,
    "v_59": 34.23703105540466,
    "v_160": 6.773740390571987,
    "v_151": 36.87786737347238,
    "v_129": 80.2645788336933,
    "v_3": 45.47142962015633,
    "v_114": 30.632851268141835,
    "v_65": 12.793095774053569,
    "v_154": 73.94543828264759,
    "v_49": 78.05171865320543,
    "v_93": 0.0,
    "v_44": 77.4210436624169,
    "v_134": 55.81220064112223,
    "v_34": 79.54429320073,
    "v_100": 90.05677048519482,
    "v_170": 82.17520708978674,
    "v_142": 93.36440355940144,
    "v_77": 60.423971377459765,
    "v_35": 69.22318472125092,
    "v_91": 39.26386404293382,
    "v_16": 95.79133905423522,
    "v_146": 100.57602862254025,
    "v_133": 141.6347863548376,
    "v_190": 123.22702527268302,
    "v_1": 131.6088336546672,
    "v_115": 120.81574239713774,
    "v_89": 131.80254259444575,
    "v_80": 96.39355992844365,
    "v_26": 88.13230390584852,
    "v_172": 123.11101164595105,
    "v_67": 123.37957707569443,
    "v_43": 107.2731865887223,
    "v_188": 147.95211288284773,
    "v_36": 147.0377081103637,
    "v_189": 138.18561055366018,
    "v_181": 132.3175753725239,
    "v_48": 110.68382293280578,
    "v_127": 117.67173524150266,
    "v_37": 130.58103924136873,
    "v_197": 131.11936960235664,
    "v_173": 182.55059945830453,
    "v_191": 170.00894454382825,
    "v_41": 176.9757904877449,
    "v_53": 205.00357781753132,
    "v_161": 203.44007155635063,
    "v_185": 117.14311270125222,
    "v_45": 168.61538461538464,
    "v_32": 142.44580920109576,
    "v_88": 166.36113354223255,
    "v_95": 178.7001684587952,
    "v_103": 239.72445717759393,
    "v_31": 197.80481575785208,
    "v_166": 183.1048250308133,
    "v_42": 235.81570891144452,
    "v_152": 155.6055456171735,
    "v_66": 195.48687296429523,
    "v_138": 152.4412248809004,
    "v_98": 228.76544817380622,
    "v_104": 198.7440231257349,
    "v_112": 199.86671663762428,
    "v_69": 185.46992727165014,
    "v_62": 191.35605208828372,
    "v_84": 261.9577004859289,
    "v_56": 190.67774401011968,
    "v_61": 225.92916101595594,
    "v_159": 295.24698660958643,
    "v_13": 223.38440287925445,
    "v_81": 244.5918931136672,
    "v_99": 219.44607000312965,
    "v_102": 238.27732593557093,
    "v_168": 243.35169508442902,
    "v_47": 260.71798679769455,
    "v_76": 222.4837387825758,
    "v_75": 262.58155376192445,
    "v_113": 246.49616009252355,
    "v_110": 206.3955574788364,
    "v_135": 297.2704298146309,
    "v_74": 243.47271753143468,
    "v_86": 166.91125490101595,
    "v_15": 278.008545291332,
    "v_14": 214.75494461337544,
    "v_46": 219.93190233511191,
    "v_55": 264.5191460890642,
    "v_125": 289.5741669467874,
    "v_12": 285.80413509674145,
    "v_123": 301.80519250510736,
    "v_87": 272.80154639507197,
    "v_21": 243.70912588173627,
    "v_9": 317.3116841886996,
    "v_118": 237.17315323182012,
    "v_148": 310.5457839580347,
    "v_128": 334.8987708174759,
    "v_176": 311.38632251101484,
    "v_52": 266.258064049826,
    "v_183": 250.013160521398,
    "v_0": 246.68871055610717,
    "v_157": 304.9847144249927,
    "v_28": 288.7236701484005,
    "v_92": 280.24978459683865,
    "v_150": 321.1984497411943,
    "v_108": 280.12858892576605,
    "v_38": 320.2203429797923,
    "v_10": 262.5628805267486,
    "v_72": 402.5990678674308,
    "v_29": 368.69850769720176,
    "v_58": 209.7984425288911,
    "v_162": 392.06133484276535,
    "v_143": 369.5265395141654,
    "v_60": 374.597837375517,
    "v_83": 310.62644648535445,
    "v_145": 264.71908687280524,
    "v_27": 391.7902597845839,
    "v_139": 335.55031032222246,
    "v_177": 273.38225350659565,
    "v_50": 340.0005051940035,
    "v_33": 346.5376464029904,
    "v_101": 256.9851304203356,
    "v_90": 356.0121392077542,
    "v_117": 404.37360971788803,
    "v_119": 340.5831229982614,
    "v_111": 485.27665428983926,
    "v_19": 385.0863164578319,
    "v_153": 298.8744012455088,
    "v_109": 367.86653697400095
  },
  "total_rerouting_events": 0,
  "vehicle_reroutes": {},
  "congestion_levels_over_time": [
    1.0,
    1.0,
    1.0,
    1.0,
    1.0,
    1.0,
    1.0,
    1.0,
    1.0,
    1.0,
    1.0,
    1.0,
    1.0,
    1.0,
    1.0,
    1.0,
    1.0,
    1.0,
    1.0,
    1.0,
    1.0,
    1.0,
    1.0,
    1.0,
    1.0,
    1.0,
    1.0,
    1.0,
    1.0,
    1.0,
    1.0,
    1.0,
    1.0,
    1.0,
    1.0,
    1.0,
    1.0,
    1.0,
    1.0,
    1.0,
    1.0,
    1.0,
    1.0,
    1.0,
    1.0,
    1.0,
    1.0,
    1.0,
    1.0,
    1.0,
    1.0,
    1.0,
    1.0,
    1.0,
    1.0,
    1.0,
    1.0,
    1.0,
    1.0,
    1.0,
    1.0,
    1.0,
    1.0,
    1.0,
    1.0,
    1.0,
    1.0,
    1.0,
    1.0,
    1.0,
    1.0,
    1.0,
    1.0,
    1.0,
    1.0,
    1.0,
    1.0,
    1.0,
    1.0,
    1.0,
    1.0,
    1.0,
    1.0,
    1.0,
    1.0,
    1.0,
    1.0,
    1.0,
    1.0,
    1.0,
    1.0,
    1.0,
    1.0,
    1.0,
    1.0,
    1.0,
    1.0,
    1.0,
    1.0,
    1.0,
    1.0,
    1.0,
    1.0,
    1.0,
    1.0,
    1.0,
    1.0,
    1.0,
    1.0,
    1.0,
    1.0,
    1.0,
    1.0,
    1.0,
    1.0,
    1.0,
    1.0,
    1.0,
    1.0,
    1.0,
    1.0,
    1.0,
    1.0,
    1.0,
    1.0,
    1.0,
    1.0,
    1.0,
    1.0,
    1.0,
    1.0,
    1.0,
    1.0,
    1.0,
    1.0,
    1.0,
    1.0,
    1.0,
    1.0,
    1.0,
    1.0,
    1.0,
    1.0,
    1.0,
    1.0,
    1.0,
    1.0,
    1.0,
    1.0,
    1.0,
    1.0,
    1.0,
    1.0,
    1.0,
    1.0,
    1.0,
    1.0,
    1.0,
    1.0,
    1.0,
    1.0,
    1.0,
    1.0,
    1.0,
    1.0,
    1.0,
    1.0,
    1.0,
    1.0,
    1.0,
    1.0,
    1.0,
    1.0,
    1.0,
    1.0,
    1.0,
    1.0,
    1.0,
    1.0,
    1.0,
    1.0,
    1.0,
    1.0,
    1.0,
    1.0,
    1.0,
    1.0,
    1.0,
    1.0,
    1.0,
    1.0,
    1.0,
    1.0,
    1.0,
    1.0,
    1.0,
    1.0,
    1.0,
    1.0,
    1.0,
    1.0,
    1.0,
    1.0,
    1.0,
    1.0,
    1.0,
    1.0,
    1.0,
    1.0,
    1.0,
    1.0,
    1.0,
    1.0,
    1.0,
    1.0,
    1.0,
    1.0,
    1.0,
    1.0,
    1.0,
    1.0,
    1.0,
    1.0,
    1.0,
    1.0,
    1.0,
    1.0,
    1.0,
    1.0,
    1.0,
    1.0,
    1.0,
    1.0,
    1.0,
    1.0,
    1.0,
    1.0,
    1.0,
    1.0,
    1.0,
    1.0,
    1.0,
    1.0,
    1.0,
    1.0,
    1.0,
    1.0,
    1.0,
    1.0,
    1.0,
    1.0,
    1.0,
    1.0,
    1.0,
    1.0,
    1.0,
    1.0,
    1.0,
    1.0,
    1.0,
    1.0,
    1.0,
    1.0,
    1.0,
    1.0,
    1.0,
    1.0,
    1.0,
    1.0,
    1.0,
    1.0,
    1.0,
    1.0,
    1.0,
    1.0,
    1.0,
    1.0,
    1.0,
    1.0,
    1.0,
    1.0,
    1.0,
    1.0,
    1.0,
    1.0,
    1.0,
    1.0,
    1.0,
    1.0,
    1.0,
    1.0,
    1.0,
    1.0,
    1.0,
    1.0,
    1.0,
    1.0,
    1.0,
    1.0,
    1.0,
    1.0,
    1.0,
    1.0,
    1.0,
    1.0,
    1.0,
    1.0,
    1.0,
    1.0,
    1.0,
    1.0,
    1.0,
    1.0,
    1.0,
    1.0,
    1.0,
    1.0,
    1.0,
    1.0,
    1.0,
    1.0,
    1.0,
    1.0,
    1.0,
    1.0,
    1.0,
    1.0,
    1.0,
    1.0,
    1.0,
    1.0,
    1.0,
    1.0,
    1.0,
    1.0,
    1.0,
    1.0,
    1.0,
    1.0,
    1.0,
    1.0,
    1.0,
    1.0,
    1.0,
    1.0,
    1.0,
    1.0,
    1.0,
    1.0,
    1.0,
    1.0,
    1.0,
    1.0,
    1.0,
    1.0,
    1.0,
    1.0,
    1.0,
    1.0,
    1.0,
    1.0,
    1.0,
    1.0,
    1.0,
    1.0,
    1.0,
    1.0,
    1.0,
    1.0,
    1.0,
    1.0,
    1.0,
    1.0,
    1.0,
    1.0,
    1.0,
    1.0,
    1.0,
    1.0,
    1.0,
    1.0,
    1.0,
    1.0,
    1.0,
    1.0,
    1.0,
    1.0,
    1.0,
    1.0,
    1.0,
    1.0,
    1.0,
    1.0,
    1.0,
    1.0,
    1.0,
    1.0,
    1.0,
    1.0,
    1.0,
    1.0,
    1.0,
    1.0,
    1.0,
    1.0,
    1.0,
    1.0,
    1.0,
    1.0,
    1.0,
    1.0,
    1.0,
    1.0,
    1.0,
    1.0,
    1.0,
    1.0,
    1.0,
    1.0,
    1.0,
    1.0,
    1.0,
    1.0,
    1.0,
    1.0,
    1.0,
    1.0,
    1.0,
    1.0,
    1.0,
    1.0,
    1.0,
    1.0,
    1.0,
    1.0,
    1.0,
    1.0,
    1.0,
    1.0,
    1.0,
    1.0,
    1.0,
    1.0,
    1.0,
    1.0,
    1.0,
    1.0,
    1.0,
    1.0,
    1.0,
    1.0,
    1.0,
    1.0,
    1.0,
    1.0,
    1.0,
    1.0,
    1.0,
    1.0,
    1.0,
    1.0,
    1.0,
    1.0,
    1.0,
    1.0,
    1.0,
    1.0,
    1.0,
    1.0,
    1.0,
    1.0,
    1.0,
    1.0,
    1.0,
    1.0,
    1.0,
    1.0,
    1.0,
    1.0,
    1.0,
    1.0,
    1.0,
    1.0,
    1.0,
    1.0,
    1.0,
    1.0,
    1.0,
    1.0,
    1.0,
    1.0,
    1.0,
    1.0,
    1.0,
    1.0,
    1.0,
    1.0,
    1.0,
    1.0,
    1.0,
    1.0,
    1.0,
    1.0,
    1.0,
    1.0,
    1.0,
    1.0,
    1.0,
    1.0,
    1.0,
    1.0,
    1.0,
    1.0,
    1.0,
    1.0,
    1.0,
    1.0,
    1.0,
    1.0,
    1.0,
    1.0,
    1.0,
    1.0,
    1.0,
    1.0,
    1.0,
    1.0,
    1.0,
    1.0,
    1.0,
    1.0,
    1.0,
    1.0,
    1.0,
    1.0,
    1.0,
    1.0,
    1.0,
    1.0,
    1.0,
    1.0,
    1.0,
    1.0,
    1.0,
    1.0,
    1.0,
    1.0,
    1.0,
    1.0,
    1.0,
    1.0,
    1.0,
    1.0,
    1.0,
    1.0,
    1.0,
    1.0,
    1.0,
    1.0,
    1.0,
    1.0,
    1.0,
    1.0,
    1.0,
    1.0,
    1.0,
    1.0,
    1.0,
    1.0,
    1.0,
    1.0,
    1.0,
    1.0,
    1.0,
    1.0,
    1.0,
    1.0,
    1.0,
    1.0,
    1.0,
    1.0,
    1.0,
    1.0,
    1.0,
    1.0,
    1.0,
    1.0,
    1.0,
    1.0,
    1.0,
    1.0,
    1.0,
    1.0,
    1.0,
    1.0,
    1.0,
    1.0,
    1.0,
    1.0,
    1.0
  ],
  "throughput_over_time": [
    31,
    0,
    0,
    0,
    0,
    0,
    0,
    0,
    0,
    0,
    0,
    0,
    0,
    0,
    0,
    0,
    0,
    0,
    0,
    0,
    0,
    0,
    0,
    1,
    0,
    0,
    0,
    0,
    0,
    0,
    0,
    0,
    0,
    0,
    0,
    0,
    0,
    0,
    0,
    0,
    0,
    0,
    0,
    0,
    0,
    0,
    0,
    0,
    0,
    0,
    0,
    0,
    0,
    0,
    2,
    0,
    0,
    1,
    0,
    0,
    1,
    1,
    0,
    0,
    0,
    1,
    0,
    0,
    0,
    0,
    0,
    0,
    0,
    0,
    0,
    0,
    0,
    1,
    0,
    0,
    0,
    0,
    0,
    0,
    1,
    0,
    1,
    0,
    0,
    0,
    0,
    0,
    1,
    0,
    0,
    0,
    1,
    0,
    0,
    1,
    0,
    0,
    0,
    0,
    0,
    0,
    0,
    0,
    0,
    0,
    1,
    2,
    0,
    0,
    0,
    0,
    0,
    0,
    0,
    0,
    0,
    1,
    0,
    0,
    0,
    0,
    0,
    0,
    0,
    0,
    0,
    1,
    0,
    0,
    0,
    0,
    1,
    0,
    0,
    1,
    0,
    0,
    0,
    1,
    1,
    0,
    0,
    0,
    0,
    0,
    0,
    0,
    0,
    0,
    0,
    2,
    0,
    0,
    0,
    0,
    0,
    1,
    0,
    1,
    1,
    0,
    0,
    0,
    0,
    0,
    0,
    0,
    0,
    0,
    0,
    0,
    0,
    0,
    0,
    0,
    1,
    0,
    0,
    0,
    0,
    0,
    0,
    0,
    2,
    0,
    1,
    0,
    0,
    0,
    0,
    0,
    1,
    1,
    1,
    1,
    0,
    0,
    0,
    0,
    0,
    0,
    0,
    0,
    0,
    0,
    0,
    1,
    0,
    0,
    0,
    0,
    0,
    0,
    0,
    0,
    1,
    0,
    0,
    0,
    0,
    0,
    0,
    0,
    0,
    0,
    0,
    0,
    0,
    1,
    1,
    2,
    1,
    0,
    0,
    0,
    0,
    0,
    0,
    0,
    0,
    0,
    1,
    1,
    0,
    1,
    1,
    1,
    0,
    1,
    0,
    0,
    0,
    0,
    0,
    0,
    0,
    0,
    0,
    0,
    0,
    0,
    0,
    0,
    0,
    0,
    0,
    0,
    0,
    0,
    0,
    0,
    0,
    0,
    0,
    2,
    2,
    1,
    0,
    0,
    0,
    1,
    0,
    1,
    0,
    0,
    0,
    0,
    0,
    0,
    2,
    0,
    0,
    0,
    0,
    0,
    1,
    0,
    0,
    0,
    0,
    0,
    0,
    0,
    0,
    0,
    0,
    0,
    0,
    0,
    0,
    0,
    0,
    0,
    0,
    0,
    0,
    0,
    0,
    1,
    2,
    1,
    0,
    0,
    1,
    2,
    0,
    0,
    0,
    0,
    1,
    0,
    0,
    0,
    0,
    0,
    0,
    1,
    0,
    0,
    0,
    0,
    0,
    0,
    1,
    0,
    0,
    0,
    1,
    1,
    0,
    0,
    1,
    0,
    0,
    0,
    0,
    0,
    0,
    0,
    0,
    0,
    1,
    0,
    2,
    5,
    0,
    2,
    0,
    1,
    1,
    0,
    1,
    0,
    1,
    0,
    0,
    0,
    0,
    1,
    0,
    0,
    0,
    0,
    0,
    0,
    0,
    0,
    1,
    0,
    1,
    0,
    0,
    0,
    1,
    0,
    0,
    1,
    0,
    0,
    0,
    0,
    0,
    0,
    0,
    0,
    0,
    0,
    0,
    0,
    0,
    2,
    1,
    0,
    0,
    0,
    0,
    0,
    0,
    1,
    0,
    0,
    0,
    0,
    0,
    0,
    0,
    0,
    0,
    0,
    1,
    0,
    0,
    0,
    0,
    0,
    0,
    0,
    0,
    0,
    0,
    0,
    0,
    0,
    0,
    0,
    0,
    0,
    0,
    1,
    1,
    0,
    0,
    0,
    2,
    1,
    1,
    0,
    2,
    0,
    0,
    0,
    0,
    2,
    0,
    1,
    0,
    0,
    1,
    0,
    0,
    0,
    0,
    0,
    0,
    0,
    0,
    0,
    0,
    0,
    0,
    0,
    1,
    0,
    0,
    0,
    0,
    1,
    0,
    0,
    0,
    0,
    0,
    0,
    0,
    0,
    1,
    1,
    0,
    0,
    1,
    1,
    0,
    0,
    0,
    0,
    2,
    0,
    0,
    0,
    1,
    0,
    0,
    0,
    0,
    0,
    0,
    2,
    0,
    0,
    0,
    0,
    0,
    0,
    0,
    0,
    0,
    0,
    0,
    0,
    0,
    0,
    0,
    0,
    0,
    0,
    0,
    0,
    0,
    1,
    0,
    0,
    0,
    0,
    0,
    0,
    0,
    0,
    0,
    0,
    0,
    1,
    0,
    2,
    1,
    0,
    0,
    0,
    0,
    0,
    1,
    0,
    1,
    0,
    0,
    0,
    0,
    0,
    0,
    0,
    0,
    0,
    0,
    1,
    0,
    0,
    1,
    0,
    0,
    0,
    0,
    1,
    0,
    0,
    0,
    0,
    0,
    0,
    0,
    1,
    2,
    1,
    0,
    0,
    0,
    0
  ],
  "ambulance_travel_times": {},
  "ambulance_response_times": {},
  "ambulance_success_rate": 1.0,
  "emergency_corridor_activation_time": 0.0,
  "emergency_corridor_activation_count": 0,
  "packets_sent": 0,
  "packets_delivered": 0,
  "packet_delivery_ratio": 1.0,
  "message_latencies": [],
  "packet_loss_count": 0,
  "communication_overhead_per_vehicle": {},
  "vehicle_energy_consumed": {
    "v_40": 0.0,
    "v_51": 0.0,
    "v_54": 0.0,
    "v_57": 0.0,
    "v_64": 0.0,
    "v_68": 0.0,
    "v_73": 0.0,
    "v_78": 0.0,
    "v_79": 0.0,
    "v_105": 0.0,
    "v_107": 0.0,
    "v_122": 0.0,
    "v_126": 0.0,
    "v_144": 0.0,
    "v_149": 0.0,
    "v_156": 0.0,
    "v_158": 0.0,
    "v_164": 0.0,
    "v_165": 0.0,
    "v_169": 0.0,
    "v_171": 0.0,
    "v_175": 0.0,
    "v_179": 0.0,
    "v_180": 0.0,
    "v_182": 0.0,
    "v_184": 0.0,
    "v_186": 0.0,
    "v_193": 0.0,
    "v_196": 0.0,
    "v_198": 0.0,
    "v_199": 0.0,
    "v_4": 0.0992895278618627,
    "v_30": 0.13226780125060472,
    "v_120": 0.10870412052739122,
    "v_192": 0.11645458173989881,
    "v_20": 0.3839685359935663,
    "v_140": 0.26571752586697733,
    "v_163": 0.3610818099718019,
    "v_25": 0.10281563916890696,
    "v_63": 0.09512590920705354,
    "v_6": 0.08874299044764883,
    "v_59": 0.11735476042304849,
    "v_160": 0.26258908072403925,
    "v_151": 0.22994440592703042,
    "v_129": 0.2271762664542208,
    "v_3": 0.1376262499282746,
    "v_114": 0.2679904087722593,
    "v_65": 0.2648133591695246,
    "v_154": 0.11843095447161331,
    "v_49": 0.3599357135991171,
    "v_93": 0.0,
    "v_44": 0.2990182841830167,
    "v_134": 0.2045104606241221,
    "v_34": 0.28339437637193593,
    "v_100": 0.17552586448195637,
    "v_170": 0.44074676783105016,
    "v_142": 0.3021550302543707,
    "v_77": 0.1858975584121077,
    "v_35": 0.2602581864580088,
    "v_91": 0.2268796653145481,
    "v_16": 0.282823122296782,
    "v_146": 0.208636125552481,
    "v_133": 0.49384620122405,
    "v_190": 0.4916182727383451,
    "v_1": 0.49318510499735574,
    "v_115": 0.14319885745568045,
    "v_89": 0.2692069338456333,
    "v_80": 0.20320526888940366,
    "v_26": 0.2806165536498084,
    "v_172": 0.32783292124265,
    "v_67": 0.26057403683692,
    "v_43": 0.30387075801347996,
    "v_188": 0.30511142982412315,
    "v_36": 0.2188552259396183,
    "v_189": 0.42794919082153604,
    "v_181": 0.3108406352930534,
    "v_48": 0.4789599467151529,
    "v_127": 0.24240186752075207,
    "v_37": 0.42563214232770746,
    "v_197": 0.39395003359397407,
    "v_173": 0.23907235416123745,
    "v_191": 0.2516858357575819,
    "v_41": 0.5726341763825209,
    "v_53": 0.17094586480453156,
    "v_161": 0.17646763389748563,
    "v_185": 0.30098775445984827,
    "v_45": 0.24091613793262032,
    "v_32": 0.4899936919799539,
    "v_88": 0.2277449452408518,
    "v_95": 0.5846938854746018,
    "v_103": 0.27026532170572526,
    "v_31": 0.38342685379039815,
    "v_166": 0.3202571292410663,
    "v_42": 0.4865856133510108,
    "v_152": 0.2500770677646628,
    "v_66": 0.279272240126826,
    "v_138": 0.40057205003072804,
    "v_98": 0.2348935639584147,
    "v_104": 0.6229515583886687,
    "v_112": 0.4728597563196039,
    "v_69": 0.32018854507440914,
    "v_62": 0.31014213296675375,
    "v_84": 0.4127478782997813,
    "v_56": 0.4941392875526978,
    "v_61": 0.4780074207441407,
    "v_159": 0.4488164919545888,
    "v_13": 0.5955504646329541,
    "v_81": 0.605687683976199,
    "v_99": 0.40106984118446437,
    "v_102": 0.5384786891682841,
    "v_168": 0.44604559967085256,
    "v_47": 0.6411462830447842,
    "v_76": 0.49835265581055743,
    "v_75": 0.9880952908819816,
    "v_113": 0.308951366202876,
    "v_110": 0.6280455856311468,
    "v_135": 0.7075041558127321,
    "v_74": 0.3235219655704451,
    "v_86": 0.5224119423273774,
    "v_15": 0.5171762494838161,
    "v_14": 0.5228054576902397,
    "v_46": 0.4416645752990896,
    "v_55": 0.49371953892959664,
    "v_125": 0.33246304685850125,
    "v_12": 0.39215861067292573,
    "v_123": 0.42249695125885595,
    "v_87": 0.3957976503876144,
    "v_21": 0.39667453893576743,
    "v_9": 0.5226749382945833,
    "v_118": 0.45062201177511124,
    "v_148": 0.44874701932463734,
    "v_128": 0.38189304816762454,
    "v_176": 0.5329506960687245,
    "v_52": 0.5626949490341198,
    "v_183": 0.4938290671000522,
    "v_0": 0.6341805892489566,
    "v_157": 0.41622826053147527,
    "v_28": 0.6419400307498623,
    "v_92": 0.43238534254951705,
    "v_150": 0.5305316433184992,
    "v_108": 0.4940846405706406,
    "v_38": 0.5421742586150792,
    "v_10": 0.7932612991637419,
    "v_72": 0.33294244824413805,
    "v_29": 0.32473693269406195,
    "v_58": 0.19706675098987894,
    "v_162": 0.37986075655222307,
    "v_143": 0.5528040604020409,
    "v_60": 0.6071316831319181,
    "v_83": 0.5462688847075967,
    "v_145": 0.6404255875904007,
    "v_27": 0.6921703915153529,
    "v_139": 0.8192325996361252,
    "v_177": 0.5572027035798067,
    "v_50": 0.5024531042369202,
    "v_33": 0.6397297163990253,
    "v_101": 0.6426468103267783,
    "v_90": 0.6443742338893087,
    "v_117": 0.8459364732947554,
    "v_119": 0.4339646634252767,
    "v_111": 0.8185794848672543,
    "v_19": 0.7148383912347694,
    "v_153": 0.6907068370222779,
    "v_109": 0.44493718200881127
  },
  "vehicle_travelled_distance": {
    "v_40": 1011.0699999999999,
    "v_51": 1682.97,
    "v_54": 1188.45,
    "v_57": 796.27,
    "v_64": 1797.44,
    "v_68": 1029.9,
    "v_73": 1903.81,
    "v_78": 2834.56,
    "v_79": 2142.39,
    "v_105": 1552.95,
    "v_107": 2991.43,
    "v_122": 1287.9,
    "v_126": 1165.77,
    "v_144": 2096.66,
    "v_149": 19371.51,
    "v_156": 2778.07,
    "v_158": 3233.56,
    "v_164": 2021.5,
    "v_165": 6228.51,
    "v_169": 1842.69,
    "v_171": 606.4,
    "v_175": 2771.4,
    "v_179": 2093.36,
    "v_180": 2636.21,
    "v_182": 2879.69,
    "v_184": 1443.01,
    "v_186": 7710.4,
    "v_193": 2196.56,
    "v_196": 1290.48,
    "v_198": 2206.89,
    "v_199": 3611.96,
    "v_4": 280.64,
    "v_30": 391.37,
    "v_120": 231.89,
    "v_192": 467.90000000000003,
    "v_20": 848.99,
    "v_140": 633.1,
    "v_163": 900.73,
    "v_25": 464.92,
    "v_63": 611.56,
    "v_6": 626.46,
    "v_59": 681.88,
    "v_160": 1318.01,
    "v_151": 948.13,
    "v_129": 670.12,
    "v_3": 755.94,
    "v_114": 1136.63,
    "v_65": 1594.15,
    "v_154": 637.87,
    "v_49": 1333.78,
    "v_93": 1657.14,
    "v_44": 1308.47,
    "v_134": 1021.77,
    "v_34": 906.34,
    "v_100": 882.58,
    "v_170": 1578.68,
    "v_142": 1154.87,
    "v_77": 1146.8,
    "v_35": 1244.84,
    "v_91": 1573.43,
    "v_16": 1343.83,
    "v_146": 977.4,
    "v_133": 1215.73,
    "v_190": 1545.92,
    "v_1": 1291.87,
    "v_115": 862.92,
    "v_89": 992.26,
    "v_80": 1281.3,
    "v_26": 1564.94,
    "v_172": 1555.4,
    "v_67": 1335.44,
    "v_43": 1521.9099999999999,
    "v_188": 1231.32,
    "v_36": 1011.79,
    "v_189": 1651.85,
    "v_181": 1598.13,
    "v_48": 2267.22,
    "v_127": 1479.43,
    "v_37": 1857.0,
    "v_197": 1867.05,
    "v_173": 1105.23,
    "v_191": 1218.52,
    "v_41": 2151.39,
    "v_53": 838.46,
    "v_161": 867.12,
    "v_185": 1876.6399999999999,
    "v_45": 1323.54,
    "v_32": 2316.84,
    "v_88": 1441.53,
    "v_95": 2083.7799999999997,
    "v_103": 1019.53,
    "v_31": 1737.94,
    "v_166": 1766.1599999999999,
    "v_42": 1765.73,
    "v_152": 1927.37,
    "v_66": 1505.46,
    "v_138": 2088.11,
    "v_98": 1212.8,
    "v_104": 2036.87,
    "v_112": 2169.7799999999997,
    "v_69": 1960.65,
    "v_62": 1870.0,
    "v_84": 1486.98,
    "v_56": 2234.15,
    "v_61": 1987.62,
    "v_159": 1330.1,
    "v_13": 2125.95,
    "v_81": 2218.11,
    "v_99": 1962.54,
    "v_102": 2057.28,
    "v_168": 1836.3600000000001,
    "v_47": 2087.2,
    "v_76": 2162.5099999999998,
    "v_75": 2637.27,
    "v_113": 1533.66,
    "v_110": 2712.23,
    "v_135": 2123.29,
    "v_74": 1801.14,
    "v_86": 3392.95,
    "v_15": 2030.84,
    "v_14": 2594.46,
    "v_46": 2289.29,
    "v_55": 2265.88,
    "v_125": 1599.46,
    "v_12": 1506.31,
    "v_123": 1609.12,
    "v_87": 2229.09,
    "v_21": 2665.31,
    "v_9": 2087.97,
    "v_118": 2759.67,
    "v_148": 1928.53,
    "v_128": 1417.65,
    "v_176": 2181.98,
    "v_52": 2598.7599999999998,
    "v_183": 2674.2400000000002,
    "v_0": 2769.62,
    "v_157": 2129.39,
    "v_28": 2680.35,
    "v_92": 2253.11,
    "v_150": 2388.29,
    "v_108": 2764.86,
    "v_38": 2524.69,
    "v_10": 3448.4,
    "v_72": 1147.45,
    "v_29": 1563.97,
    "v_58": 3688.11,
    "v_162": 1563.55,
    "v_143": 2062.49,
    "v_60": 2201.99,
    "v_83": 2600.47,
    "v_145": 3553.78,
    "v_27": 2132.98,
    "v_139": 3668.94,
    "v_177": 3289.62,
    "v_50": 2580.75,
    "v_33": 2639.62,
    "v_101": 3590.4,
    "v_90": 2913.3,
    "v_117": 3362.32,
    "v_119": 3005.38,
    "v_111": 2237.21,
    "v_19": 2907.13,
    "v_153": 3814.04,
    "v_109": 2753.55
  },
  "charging_queue_lengths_over_time": [
    0.0,
    0.0,
    0.0,
    0.0,
    0.0,
    0.0,
    0.0,
    0.0,
    0.0,
    0.0,
    0.0,
    0.0,
    0.0,
    0.0,
    0.0,
    0.0,
    0.0,
    0.0,
    0.0,
    0.0,
    0.0,
    0.0,
    0.0,
    0.0,
    0.0,
    0.0,
    0.0,
    0.0,
    0.0,
    0.0,
    0.0,
    0.0,
    0.0,
    0.0,
    0.0,
    0.0,
    0.0,
    0.0,
    0.0,
    0.0,
    0.0,
    0.0,
    0.0,
    0.0,
    0.0,
    0.0,
    0.0,
    0.0,
    0.0,
    0.0,
    0.0,
    0.0,
    0.0,
    0.0,
    0.0,
    0.0,
    0.0,
    0.0,
    0.0,
    0.0,
    0.0,
    0.0,
    0.0,
    0.0,
    0.0,
    0.0,
    0.0,
    0.0,
    0.0,
    0.0,
    0.0,
    0.0,
    0.0,
    0.0,
    0.0,
    0.0,
    0.0,
    0.0,
    0.0,
    0.0,
    0.0,
    0.0,
    0.0,
    0.0,
    0.0,
    0.0,
    0.0,
    0.0,
    0.0,
    0.0,
    0.0,
    0.0,
    0.0,
    0.0,
    0.0,
    0.0,
    0.0,
    0.0,
    0.0,
    0.0,
    0.0,
    0.0,
    0.0,
    0.0,
    0.0,
    0.0,
    0.0,
    0.0,
    0.0,
    0.0,
    0.0,
    0.0,
    0.0,
    0.0,
    0.0,
    0.0,
    0.0,
    0.0,
    0.0,
    0.0,
    0.0,
    0.0,
    0.0,
    0.0,
    0.0,
    0.0,
    0.0,
    0.0,
    0.0,
    0.0,
    0.0,
    0.0,
    0.0,
    0.0,
    0.0,
    0.0,
    0.0,
    0.0,
    0.0,
    0.0,
    0.0,
    0.0,
    0.0,
    0.0,
    0.0,
    0.0,
    0.0,
    0.0,
    0.0,
    0.0,
    0.0,
    0.0,
    0.0,
    0.0,
    0.0,
    0.0,
    0.0,
    0.0,
    0.0,
    0.0,
    0.0,
    0.0,
    0.0,
    0.0,
    0.0,
    0.0,
    0.0,
    0.0,
    0.0,
    0.0,
    0.0,
    0.0,
    0.0,
    0.0,
    0.0,
    0.0,
    0.0,
    0.0,
    0.0,
    0.0,
    0.0,
    0.0,
    0.0,
    0.0,
    0.0,
    0.0,
    0.0,
    0.0,
    0.0,
    0.0,
    0.0,
    0.0,
    0.0,
    0.0,
    0.0,
    0.0,
    0.0,
    0.0,
    0.0,
    0.0,
    0.0,
    0.0,
    0.0,
    0.0,
    0.0,
    0.0,
    0.0,
    0.0,
    0.0,
    0.0,
    0.0,
    0.0,
    0.0,
    0.0,
    0.0,
    0.0,
    0.0,
    0.0,
    0.0,
    0.0,
    0.0,
    0.0,
    0.0,
    0.0,
    0.0,
    0.0,
    0.0,
    0.0,
    0.0,
    0.0,
    0.0,
    0.0,
    0.0,
    0.0,
    0.0,
    0.0,
    0.0,
    0.0,
    0.0,
    0.0,
    0.0,
    0.0,
    0.0,
    0.0,
    0.0,
    0.0,
    0.0,
    0.0,
    0.0,
    0.0,
    0.0,
    0.0,
    0.0,
    0.0,
    0.0,
    0.0,
    0.0,
    0.0,
    0.0,
    0.0,
    0.0,
    0.0,
    0.0,
    0.0,
    0.0,
    0.0,
    0.0,
    0.0,
    0.0,
    0.0,
    0.0,
    0.0,
    0.0,
    0.0,
    0.0,
    0.0,
    0.0,
    0.0,
    0.0,
    0.0,
    0.0,
    0.0,
    0.0,
    0.0,
    0.0,
    0.0,
    0.0,
    0.0,
    0.0,
    0.0,
    0.0,
    0.0,
    0.0,
    0.0,
    0.0,
    0.0,
    0.0,
    0.0,
    0.0,
    0.0,
    0.0,
    0.0,
    0.0,
    0.0,
    0.0,
    0.0,
    0.0,
    0.0,
    0.0,
    0.0,
    0.0,
    0.0,
    0.0,
    0.0,
    0.0,
    0.0,
    0.0,
    0.0,
    0.0,
    0.0,
    0.0,
    0.0,
    0.0,
    0.0,
    0.0,
    0.0,
    0.0,
    0.0,
    0.0,
    0.0,
    0.0,
    0.0,
    0.0,
    0.0,
    0.0,
    0.0,
    0.0,
    0.0,
    0.0,
    0.0,
    0.0,
    0.0,
    0.0,
    0.0,
    0.0,
    0.0,
    0.0,
    0.0,
    0.0,
    0.0,
    0.0,
    0.0,
    0.0,
    0.0,
    0.0,
    0.0,
    0.0,
    0.0,
    0.0,
    0.0,
    0.0,
    0.0,
    0.0,
    0.0,
    0.0,
    0.0,
    0.0,
    0.0,
    0.0,
    0.0,
    0.0,
    0.0,
    0.0,
    0.0,
    0.0,
    0.0,
    0.0,
    0.0,
    0.0,
    0.0,
    0.0,
    0.0,
    0.0,
    0.0,
    0.0,
    0.0,
    0.0,
    0.0,
    0.0,
    0.0,
    0.0,
    0.0,
    0.0,
    0.0,
    0.0,
    0.0,
    0.0,
    0.0,
    0.0,
    0.0,
    0.0,
    0.0,
    0.0,
    0.0,
    0.0,
    0.0,
    0.0,
    0.0,
    0.0,
    0.0,
    0.0,
    0.0,
    0.0,
    0.0,
    0.0,
    0.0,
    0.0,
    0.0,
    0.0,
    0.0,
    0.0,
    0.0,
    0.0,
    0.0,
    0.0,
    0.0,
    0.0,
    0.0,
    0.0,
    0.0,
    0.0,
    0.0,
    0.0,
    0.0,
    0.0,
    0.0,
    0.0,
    0.0,
    0.0,
    0.0,
    0.0,
    0.0,
    0.0,
    0.0,
    0.0,
    0.0,
    0.0,
    0.0,
    0.0,
    0.0,
    0.0,
    0.0,
    0.0,
    0.0,
    0.0,
    0.0,
    0.0,
    0.0,
    0.0,
    0.0,
    0.0,
    0.0,
    0.0,
    0.0,
    0.0,
    0.0,
    0.0,
    0.0,
    0.0,
    0.0,
    0.0,
    0.0,
    0.0,
    0.0,
    0.0,
    0.0,
    0.0,
    0.0,
    0.0,
    0.0,
    0.0,
    0.0,
    0.0,
    0.0,
    0.0,
    0.0,
    0.0,
    0.0,
    0.0,
    0.0,
    0.0,
    0.0,
    0.0,
    0.0,
    0.0,
    0.0,
    0.0,
    0.0,
    0.0,
    0.0,
    0.0,
    0.0,
    0.0,
    0.0,
    0.0,
    0.0,
    0.0,
    0.0,
    0.0,
    0.0,
    0.0,
    0.0,
    0.0,
    0.0,
    0.0,
    0.0,
    0.0,
    0.0,
    0.0,
    0.0,
    0.0,
    0.0,
    0.0,
    0.0,
    0.0,
    0.0,
    0.0,
    0.0,
    0.0,
    0.0,
    0.0,
    0.0,
    0.0,
    0.0,
    0.0,
    0.0,
    0.0,
    0.0,
    0.0,
    0.0,
    0.0,
    0.0,
    0.0,
    0.0,
    0.0,
    0.0,
    0.0,
    0.0,
    0.0,
    0.0,
    0.0,
    0.0,
    0.0,
    0.0,
    0.0,
    0.0,
    0.0,
    0.0,
    0.0,
    0.0,
    0.0,
    0.0,
    0.0,
    0.0,
    0.0,
    0.0,
    0.0,
    0.0,
    0.0,
    0.0,
    0.0,
    0.0,
    0.0,
    0.0,
    0.0,
    0.0,
    0.0,
    0.0,
    0.0,
    0.0,
    0.0,
    0.0,
    0.0,
    0.0,
    0.0,
    0.0,
    0.0,
    0.0,
    0.0,
    0.0,
    0.0,
    0.0,
    0.0,
    0.0,
    0.0,
    0.0,
    0.0,
    0.0,
    0.0,
    0.0
  ],
  "stranded_vehicle_count": 0,
  "total_charging_events": 0,
  "vehicle_charging_events": {},
  "router_execution_times": [
    0.3869009359914344,
    0.6001040089904564,
    0.62417709500005,
    0.4879114409995964,
    0.013250170988612808,
    0.24222088798705954,
    0.060551765011041425,
    0.6267074409988709,
    0.42337366299761925,
    0.24424731799808796,
    0.5273721020057565,
    0.11079461099870969,
    0.3252895890036598,
    0.6117581409926061,
    0.27290382600040175,
    0.5996775009989506,
    0.18125312399934046,
    0.49352680300944485,
    0.9591114280046895,
    0.4042095379991224,
    0.6565560110029764,
    0.3808794950018637,
    0.38217874300607946,
    0.24115026999788824,
    0.6977761579910293,
    0.024195786012569442,
    0.6873410690022865,
    0.3579338889976498,
    0.4006807760015363,
    0.2878300529991975,
    0.15980391899938695,
    0.21033644200360868,
    0.3910636340006022,
    0.3687232429947471,
    0.26334049500292167,
    0.10842697799671441,
    0.22601698200742248,
    0.11891368099895772,
    0.11616876001062337,
    0.3607340840098914,
    0.06779791800363455,
    0.23396406300889794,
    0.5598430060053943,
    0.2178330539900344,
    0.3524564190011006,
    0.09494725000695325,
    0.08708911499707028,
    0.24296466799569316,
    0.0835023440013174,
    0.30908888700651005,
    0.23426312499213964,
    0.19253595000191126,
    0.3451810250116978,
    0.2934575780091109,
    1.0560687840043101,
    0.4398232880048454,
    0.3789850169996498,
    0.06862294400343671,
    0.6655713830114109,
    0.0334433509997325,
    0.25257346700527705,
    0.28057203300704714,
    0.3037166870053625,
    0.24668934399960563,
    0.15575737600738648,
    0.05187153400038369,
    0.021017118997406214,
    0.08571083701099269,
    0.261927742001717,
    0.12139649099844974,
    0.759670964005636,
    0.2615252440009499,
    0.133218292001402,
    0.19019983400357887,
    0.5757976549939485,
    0.2313119460013695,
    0.924194755993085,
    0.12816431900137104,
    0.509811369003728,
    0.7988152489997447,
    0.10248855000827461,
    0.18288075999589637,
    0.2887883110088296,
    0.18528861700906418,
    0.09327729299548082,
    0.4413853080041008,
    0.4740790689975256,
    0.5533996089943685,
    0.3925913339917315,
    0.4240916459966684,
    0.23474190499109682,
    0.09844731100019999,
    0.5442597270011902,
    0.3069344980031019,
    0.08742752399120945,
    0.34802258999843616,
    0.43298954400233924,
    0.2377170749969082,
    0.6863990090059815,
    0.20832927999435924,
    0.1471479640022153,
    0.9452827829954913,
    0.1656039669906022,
    0.1805344280001009,
    0.2690244870027527,
    0.09341790000326,
    0.3998208050034009,
    0.1433455100050196,
    0.38219208898954093,
    0.0912939300033031,
    0.4247705719899386,
    0.07941741599643137,
    0.4557348579983227,
    0.2795096680056304,
    0.38013268500799313,
    0.17980709999392275,
    0.6170530630042776,
    0.12180634899414144,
    0.6239870760036865,
    0.3167268520046491,
    0.016164346001460217,
    0.6870433990115998,
    0.0684890820120927,
    0.0975501820066711,
    0.28751408999960404,
    0.6699869570002193,
    0.20347832200059202,
    0.29138268099632114,
    0.3756413579976652,
    0.05606540699955076,
    0.3506816260050982,
    0.1718251029960811,
    0.3295754729915643,
    0.05067238300398458,
    0.08971134400053415,
    0.0648063370026648,
    0.48450398100249004,
    0.7519736849935725,
    1.4187850159942172,
    0.859631300001638,
    0.05387321699527092,
    1.1196066950069508,
    0.7131779979972634,
    0.03543067899590824,
    1.5584594769898104,
    0.6999590269988403,
    0.5675360829918645,
    0.7166104720090516,
    0.09171282399620395,
    0.3919787730119424,
    0.5319931519916281,
    0.42797771500772797,
    0.06242743899929337,
    0.23510451600304805,
    0.028149242003564723,
    1.087148601989611,
    0.38398048499948345,
    0.870507205996546,
    0.665501563998987,
    0.20454133600287605,
    0.5225380620104261,
    0.24901501600106712,
    0.398192824999569,
    0.07770223000261467,
    0.13700776899349876,
    0.3452656969893724,
    0.42383292999875266,
    0.1942475099931471,
    0.3805762219999451,
    0.6049486190022435,
    0.23553449800238013,
    0.05442176399810705,
    0.10123033200216014,
    0.2616344830021262,
    0.4682920649938751,
    0.4364576290099649,
    0.41228065099858213,
    0.37726398899394553,
    0.09695000998908654,
    0.3974374550016364,
    0.35985775299195666,
    0.06073485501110554,
    0.1741872999991756,
    0.6445312270079739,
    0.07934023800771683,
    0.1197546479961602,
    0.9156771779962583,
    0.4180428249965189,
    0.12101617400185205,
    0.09503890400810633,
    0.17998388700652868,
    0.04956725100055337,
    0.038740155010600574,
    0.5198946250020526,
    0.11035834898939356,
    0.15704206500959117,
    0.08610990601300728,
    0.07576246200187597,
    0.08213046900345944,
    0.6458471710066078
  ],
  "router_convergence_speeds": [],
  "adaptation_times_after_disruptions": [],
  "route_stability_metrics": [],
  "subsystem_contributions": [],
  "exploration_ratios": [],
  "vehicles": 200,
  "experiment_metadata": {
    "python_version": "3.12.3 (main, Jun 19 2026, 12:46:00) [GCC 13.3.0]",
    "sumo_version": "Eclipse SUMO sumo 1.27.1",
    "os_info": "Linux-6.17.0-35-generic-x86_64-with-glibc2.39",
    "cpu_info": "x86_64 (4 cores)",
    "random_seed": 9,
    "network_file_path": "data/networks/midtown_manhattan.net.xml",
    "network_sha256": "c2f5702163acf3377f74e03e4bce9598f17aeab54f245edc3daf12de8bf63275",
    "git_commit": "c40f23f73f4d46d41645c27d20c2359d05da2443"
  }
}