{
  "algorithm_name": "E3HybridRouter",
  "scenario_name": "Emergency Incident Scenario",
  "seed": 1,
  "config_details": {
    "name": "Emergency Incident Scenario",
    "simulation": {
      "dt": 1.0,
      "max_steps": 600,
      "mode": "sumo",
      "network_file_path": "data/networks/midtown_manhattan.net.xml",
      "osm_file": null,
      "network_file": "data/networks/midtown_manhattan.net.xml",
      "route_file": null,
      "scenario_file": "data/scenarios/manhattan.yaml",
      "output_dir": "outputs",
      "sumo_binary": "sumo",
      "use_gui": false,
      "step_length": 1.0,
      "seed": 1,
      "traci_port": 8912,
      "output_directory": "outputs",
      "enable_subscriptions": true,
      "real_time_factor": -1.0,
      "breakdown_probability": 0.0
    },
    "battery": {
      "capacity_kwh": 60.0,
      "mass_kg": 1500.0,
      "efficiency": 0.9,
      "drag_coeff": 0.25,
      "frontal_area": 2.2,
      "rolling_res_coeff": 0.01,
      "regen_efficiency": 0.7
    },
    "charging_stations": [
      {
        "id": "station_west",
        "node_id": "42432825",
        "capacity": 4,
        "power_kw": 150.0,
        "base_price_per_kwh": 0.35
      },
      {
        "id": "station_east",
        "node_id": "42437644",
        "capacity": 4,
        "power_kw": 150.0,
        "base_price_per_kwh": 0.35
      }
    ],
    "communication": {
      "v2v_range_m": 150.0,
      "v2i_range_m": 300.0,
      "base_packet_loss_rate": 0.05,
      "base_latency_s": 0.002,
      "latency_jitter_s": 0.001,
      "propagation_speed_m_s": 300000000.0,
      "blackout_start_time": null,
      "blackout_end_time": null,
      "blackout_area": null
    },
    "emergencies": [
      {
        "id": "incident_midtown",
        "epicenter_node_id": "42432818",
        "start_time": 80.0,
        "duration": 800.0,
        "initial_radius_m": 15.0,
        "propagation_rate": 1.5,
        "intensity": 0.8
      }
    ],
    "infrastructure_failures": [],
    "ambulance_dispatches": [
      {
        "id": "amb_0",
        "start_time": 100.0,
        "origin_node_id": "9971314382",
        "destination_node_id": "42445382",
        "battery_capacity_kwh": 80.0,
        "initial_soc": 0.95,
        "v2v_range_m": 200.0,
        "v2i_range_m": 400.0,
        "speed_m_s": 25.0,
        "route": [
          "-1088325196#1",
          "-1088325194"
        ]
      }
    ],
    "road_closures": [],
    "algorithms": {
      "objectives": {
        "w_time": 0.0,
        "w_distance": 0.0,
        "w_energy": 1.0,
        "w_congestion": 0.0,
        "w_emergency": 0.0
      },
      "aco": {
        "num_ants": 5,
        "max_iterations": 5,
        "alpha": 1.0,
        "beta": 2.0,
        "q_zero": 0.9,
        "evaporation_rate": 0.1,
        "local_evaporation_rate": 0.1,
        "q": 1.0,
        "initial_pheromone": 0.1,
        "min_pheromone": 1e-06,
        "max_pheromone": 10.0,
        "evaporation_dt": 1.0,
        "collect_metrics": false
      },
      "bco": {
        "colony_size": 5,
        "max_iterations": 5,
        "scout_ratio": 0.2,
        "recruitment_factor": 0.5,
        "abandonment_threshold": 0.2,
        "elite_route_seeding": false,
        "collect_metrics": false
      },
      "pso": {
        "swarm_size": 5,
        "max_iterations": 5,
        "inertia_weight": 0.7,
        "cognitive_weight": 1.5,
        "social_weight": 1.5,
        "v_max": 5.0,
        "collect_metrics": false
      },
      "e3_hybrid": {
        "max_iterations": 5,
        "collect_metrics": true,
        "share_aco_to_pso": true,
        "share_gbest_to_pso": true,
        "share_gbest_to_bco": true,
        "share_bco_pso_to_aco": true,
        "disable_aco": false,
        "disable_bco": false,
        "disable_pso": false,
        "disable_elite_sharing": false,
        "enable_adaptive_weighting": false
      }
    }
  },
  "timestamp": "2026-07-15T18:32:36.230671",
  "ablation_settings": {
    "share_aco_to_pso": true,
    "share_gbest_to_pso": true,
    "share_gbest_to_bco": true,
    "share_bco_pso_to_aco": true
  },
  "cpu_utilization_percent": 0.0,
  "memory_usage_mb": 0.0,
  "vehicle_travel_times": {
    "v_42": 0.0,
    "v_55": 0.0,
    "v_59": 0.0,
    "v_67": 0.0,
    "v_76": 0.0,
    "v_82": 0.0,
    "v_92": 0.0,
    "v_95": 0.0,
    "v_108": 0.0,
    "v_123": 0.0,
    "v_130": 0.0,
    "v_134": 0.0,
    "v_136": 0.0,
    "v_145": 0.0,
    "v_152": 0.0,
    "v_156": 0.0,
    "v_157": 0.0,
    "v_158": 0.0,
    "v_159": 0.0,
    "v_166": 0.0,
    "v_170": 0.0,
    "v_178": 0.0,
    "v_181": 0.0,
    "v_184": 0.0,
    "v_185": 0.0,
    "v_188": 0.0,
    "v_194": 0.0,
    "v_199": 0.0,
    "v_148": 12.0,
    "v_34": 50.0,
    "v_174": 68.0,
    "v_27": 79.0,
    "v_164": 86.0,
    "v_129": 100.0,
    "v_43": 105.0,
    "v_5": 106.0,
    "v_135": 108.0,
    "v_151": 110.0,
    "v_197": 110.0,
    "v_56": 115.0,
    "v_106": 118.0,
    "v_75": 130.0,
    "v_193": 132.0,
    "v_32": 141.0,
    "v_11": 142.0,
    "v_109": 148.0,
    "v_119": 150.0,
    "v_144": 151.0,
    "v_93": 152.0,
    "v_124": 152.0,
    "v_112": 154.0,
    "v_113": 160.0,
    "v_83": 163.0,
    "v_20": 179.0,
    "v_94": 184.0,
    "v_96": 185.0,
    "v_155": 187.0,
    "v_79": 188.0,
    "v_172": 192.0,
    "v_81": 197.0,
    "v_9": 203.0,
    "v_12": 203.0,
    "v_98": 206.0,
    "v_121": 206.0,
    "v_65": 210.0,
    "v_28": 211.0,
    "v_66": 212.0,
    "v_44": 215.0,
    "v_102": 224.0,
    "v_111": 231.0,
    "v_69": 232.0,
    "v_17": 233.0,
    "v_91": 233.0,
    "v_60": 234.0,
    "v_103": 234.0,
    "v_132": 234.0,
    "v_137": 234.0,
    "v_2": 235.0,
    "v_16": 236.0,
    "v_101": 239.0,
    "v_175": 239.0,
    "v_162": 242.0,
    "v_126": 253.0,
    "v_13": 266.0,
    "v_150": 267.0,
    "v_15": 280.0,
    "v_35": 280.0,
    "v_80": 284.0,
    "v_84": 285.0,
    "v_195": 285.0,
    "v_22": 286.0,
    "v_88": 290.0,
    "v_61": 292.0,
    "v_31": 293.0,
    "v_141": 293.0,
    "v_183": 295.0,
    "v_21": 298.0,
    "v_39": 299.0,
    "v_4": 306.0,
    "v_36": 315.0,
    "v_3": 317.0,
    "v_87": 322.0,
    "v_110": 322.0,
    "v_62": 323.0,
    "v_127": 323.0,
    "v_14": 324.0,
    "v_179": 324.0,
    "v_161": 325.0,
    "v_169": 325.0,
    "v_149": 328.0,
    "v_168": 328.0,
    "v_1": 331.0,
    "v_107": 331.0,
    "v_165": 332.0,
    "v_49": 342.0,
    "v_47": 353.0,
    "v_0": 360.0,
    "v_89": 363.0,
    "v_64": 366.0,
    "v_24": 367.0,
    "v_86": 368.0,
    "v_131": 369.0,
    "v_180": 369.0,
    "v_187": 369.0,
    "v_6": 370.0,
    "v_163": 370.0,
    "v_30": 371.0,
    "v_160": 376.0,
    "v_40": 377.0,
    "v_146": 377.0,
    "v_77": 379.0,
    "v_54": 380.0,
    "v_72": 381.0,
    "v_117": 381.0,
    "v_8": 383.0,
    "v_97": 383.0,
    "v_52": 392.0,
    "v_53": 393.0,
    "v_38": 400.0,
    "v_122": 407.0,
    "v_85": 409.0,
    "v_133": 410.0,
    "v_139": 413.0,
    "v_48": 414.0,
    "v_63": 415.0,
    "v_68": 415.0,
    "v_19": 421.0,
    "v_116": 427.0,
    "v_120": 431.0,
    "v_25": 456.0,
    "v_99": 459.0,
    "v_118": 459.0,
    "v_176": 459.0,
    "v_58": 462.0,
    "v_71": 463.0,
    "v_140": 464.0,
    "v_147": 464.0,
    "v_167": 474.0,
    "v_138": 477.0,
    "v_90": 479.0,
    "v_10": 480.0,
    "v_125": 487.0,
    "v_100": 504.0,
    "v_143": 504.0,
    "v_186": 507.0,
    "v_115": 515.0,
    "v_191": 516.0,
    "v_173": 519.0,
    "v_198": 548.0,
    "v_29": 550.0,
    "v_177": 550.0,
    "v_33": 563.0,
    "v_50": 567.0,
    "v_41": 568.0,
    "v_23": 570.0,
    "v_74": 575.0,
    "v_46": 584.0,
    "v_189": 590.0,
    "v_196": 592.0,
    "v_45": 593.0,
    "v_142": 594.0
  },
  "vehicle_free_flow_times": {
    "v_42": 130.26144598950867,
    "v_55": 129.57078167199214,
    "v_59": 173.01137161263233,
    "v_67": 115.1699933414987,
    "v_76": 42.00642989705725,
    "v_82": 50.390986215457616,
    "v_92": 49.18958182808703,
    "v_95": 197.8856019246546,
    "v_108": 131.20521513913948,
    "v_123": 226.04856941858193,
    "v_130": 133.58136765874474,
    "v_134": 260.7741325595562,
    "v_136": 130.8743513756824,
    "v_145": 89.61256408968498,
    "v_152": 55.13146933934015,
    "v_156": 124.21599688840634,
    "v_157": 59.71459370906857,
    "v_158": 99.04456752583229,
    "v_159": 148.4581419909095,
    "v_166": 127.45080500894456,
    "v_170": 90.00805008944543,
    "v_178": 971.7321125222325,
    "v_181": 79.92212580059784,
    "v_184": 199.63194908629137,
    "v_185": 187.45826845480264,
    "v_188": 120.46449099814411,
    "v_194": 26.49412325793872,
    "v_199": 176.18197091638748,
    "v_148": 5.663066954643628,
    "v_34": 27.917710196779964,
    "v_174": 18.918314227169517,
    "v_27": 39.027389888016884,
    "v_164": 52.236141108711294,
    "v_129": 50.69583463734351,
    "v_43": 87.47910170764156,
    "v_5": 56.889087656529526,
    "v_135": 48.56887298747763,
    "v_151": 25.433846437186638,
    "v_197": 43.851960394152364,
    "v_56": 99.0840787119857,
    "v_106": 50.16795569353987,
    "v_75": 77.06748047716907,
    "v_193": 64.37215033530771,
    "v_32": 54.53577817531306,
    "v_11": 84.26224063076745,
    "v_109": 67.67544378202874,
    "v_119": 72.80395865289631,
    "v_144": 79.5931456073854,
    "v_93": 65.96893300414321,
    "v_124": 76.33924484610104,
    "v_112": 100.19516943116821,
    "v_113": 68.89918421670964,
    "v_83": 98.78439399266665,
    "v_20": 104.8805884251245,
    "v_94": 46.86770060184095,
    "v_96": 47.06440071556351,
    "v_155": 143.0749032462393,
    "v_79": 64.09928443649375,
    "v_172": 57.67878848761867,
    "v_81": 88.15810012479858,
    "v_9": 78.91996725318066,
    "v_12": 92.97307621472574,
    "v_98": 66.34095519227871,
    "v_121": 67.62674206099291,
    "v_65": 90.56194338084438,
    "v_28": 132.99552772808588,
    "v_66": 73.78453244312907,
    "v_44": 143.71794622769656,
    "v_102": 117.86580560152866,
    "v_111": 143.5107334525939,
    "v_69": 130.108228980322,
    "v_17": 132.54246372275907,
    "v_91": 114.88766129478873,
    "v_60": 150.36493738819325,
    "v_103": 102.84238219797516,
    "v_132": 113.60221829838585,
    "v_137": 61.49642218246869,
    "v_2": 55.21956182682487,
    "v_16": 96.4319506317849,
    "v_101": 99.39266547406082,
    "v_175": 86.68269279065905,
    "v_162": 72.47092282706829,
    "v_126": 125.32157882343705,
    "v_13": 62.88688082055403,
    "v_150": 87.42669633999932,
    "v_15": 49.898926654740606,
    "v_35": 147.18971319503743,
    "v_80": 113.9553680786038,
    "v_84": 106.44653751492368,
    "v_195": 163.54991630137422,
    "v_22": 148.65863055910816,
    "v_88": 167.83223860874674,
    "v_61": 158.1708407871199,
    "v_31": 141.07167015645965,
    "v_141": 80.5980692922026,
    "v_183": 97.54619544568814,
    "v_21": 112.60820322209645,
    "v_39": 127.74919408951756,
    "v_4": 115.78096428493235,
    "v_36": 153.59764621334767,
    "v_3": 78.69575681136665,
    "v_87": 79.4562985945024,
    "v_110": 83.7023701431256,
    "v_62": 132.76583841092358,
    "v_127": 131.47854908879225,
    "v_14": 67.84785131321874,
    "v_179": 145.2765924700979,
    "v_161": 90.60375670840786,
    "v_169": 166.1007797014879,
    "v_149": 95.10343601849955,
    "v_168": 139.21945428623312,
    "v_1": 138.14341986809214,
    "v_107": 158.233046901865,
    "v_165": 94.03898700626311,
    "v_49": 186.69678897960077,
    "v_47": 146.65638849070967,
    "v_0": 156.46554515352548,
    "v_89": 75.07549993496048,
    "v_64": 152.10017889087658,
    "v_24": 94.80769230769229,
    "v_86": 111.07550637451686,
    "v_131": 92.27326579526589,
    "v_180": 117.90920032300815,
    "v_187": 135.98021598912035,
    "v_6": 145.59408513866296,
    "v_163": 161.75719717020135,
    "v_30": 106.90060737895887,
    "v_160": 130.8096278690952,
    "v_40": 126.56681490525479,
    "v_146": 187.5778626082007,
    "v_77": 159.36259338966656,
    "v_54": 129.66222723649014,
    "v_72": 145.16584304740414,
    "v_117": 128.16357761146548,
    "v_8": 75.79851851275839,
    "v_97": 163.55224183151574,
    "v_52": 119.00376101387278,
    "v_53": 168.82400499194412,
    "v_38": 138.06950084422584,
    "v_122": 90.67480884176851,
    "v_85": 210.38591890216776,
    "v_133": 136.49724000613045,
    "v_139": 174.59490618210296,
    "v_48": 183.75794630165888,
    "v_63": 200.1674297540991,
    "v_68": 110.20560602021246,
    "v_19": 140.79033641530503,
    "v_116": 182.70584106402077,
    "v_120": 224.67004258297757,
    "v_25": 96.70420208389352,
    "v_99": 180.95217727841163,
    "v_118": 163.91091002523018,
    "v_176": 196.17907504787811,
    "v_58": 168.99073271325636,
    "v_71": 138.75314218154142,
    "v_140": 142.74491886802906,
    "v_147": 180.77876582038016,
    "v_167": 122.19451839201699,
    "v_138": 197.42219395382548,
    "v_90": 140.29560621724036,
    "v_10": 116.31470691646993,
    "v_125": 159.18741234153862,
    "v_100": 171.5746454058273,
    "v_143": 160.9234909865529,
    "v_186": 146.54128463998373,
    "v_115": 242.04006370009182,
    "v_191": 136.65902098136263,
    "v_173": 74.58430216459249,
    "v_198": 191.52369949938893,
    "v_29": 220.72361359570664,
    "v_177": 140.00729279761373,
    "v_33": 173.6700928630749,
    "v_50": 152.96176384601222,
    "v_41": 177.5886984497412,
    "v_23": 232.7540211809889,
    "v_74": 178.55246242080946,
    "v_46": 168.37726269912724,
    "v_189": 255.86809838326664,
    "v_196": 202.87275408045517,
    "v_45": 124.97418381842509,
    "v_142": 95.83856547290169
  },
  "vehicle_delays": {
    "v_42": 0.0,
    "v_55": 0.0,
    "v_59": 0.0,
    "v_67": 0.0,
    "v_76": 0.0,
    "v_82": 0.0,
    "v_92": 0.0,
    "v_95": 0.0,
    "v_108": 0.0,
    "v_123": 0.0,
    "v_130": 0.0,
    "v_134": 0.0,
    "v_136": 0.0,
    "v_145": 0.0,
    "v_152": 0.0,
    "v_156": 0.0,
    "v_157": 0.0,
    "v_158": 0.0,
    "v_159": 0.0,
    "v_166": 0.0,
    "v_170": 0.0,
    "v_178": 0.0,
    "v_181": 0.0,
    "v_184": 0.0,
    "v_185": 0.0,
    "v_188": 0.0,
    "v_194": 0.0,
    "v_199": 0.0,
    "v_148": 6.336933045356372,
    "v_34": 22.082289803220036,
    "v_174": 49.08168577283048,
    "v_27": 39.972610111983116,
    "v_164": 33.763858891288706,
    "v_129": 49.30416536265649,
    "v_43": 17.52089829235844,
    "v_5": 49.110912343470474,
    "v_135": 59.43112701252237,
    "v_151": 84.56615356281335,
    "v_197": 66.14803960584763,
    "v_56": 15.915921288014303,
    "v_106": 67.83204430646013,
    "v_75": 52.93251952283093,
    "v_193": 67.62784966469229,
    "v_32": 86.46422182468694,
    "v_11": 57.73775936923255,
    "v_109": 80.32455621797126,
    "v_119": 77.19604134710369,
    "v_144": 71.4068543926146,
    "v_93": 86.03106699585679,
    "v_124": 75.66075515389896,
    "v_112": 53.80483056883179,
    "v_113": 91.10081578329036,
    "v_83": 64.21560600733335,
    "v_20": 74.1194115748755,
    "v_94": 137.13229939815903,
    "v_96": 137.93559928443648,
    "v_155": 43.9250967537607,
    "v_79": 123.90071556350625,
    "v_172": 134.32121151238132,
    "v_81": 108.84189987520142,
    "v_9": 124.08003274681934,
    "v_12": 110.02692378527426,
    "v_98": 139.65904480772127,
    "v_121": 138.3732579390071,
    "v_65": 119.43805661915562,
    "v_28": 78.00447227191412,
    "v_66": 138.21546755687092,
    "v_44": 71.28205377230344,
    "v_102": 106.13419439847134,
    "v_111": 87.48926654740609,
    "v_69": 101.891771019678,
    "v_17": 100.45753627724093,
    "v_91": 118.11233870521127,
    "v_60": 83.63506261180675,
    "v_103": 131.15761780202484,
    "v_132": 120.39778170161415,
    "v_137": 172.50357781753132,
    "v_2": 179.78043817317513,
    "v_16": 139.5680493682151,
    "v_101": 139.60733452593917,
    "v_175": 152.31730720934095,
    "v_162": 169.5290771729317,
    "v_126": 127.67842117656295,
    "v_13": 203.11311917944596,
    "v_150": 179.57330366000068,
    "v_15": 230.1010733452594,
    "v_35": 132.81028680496257,
    "v_80": 170.04463192139622,
    "v_84": 178.55346248507632,
    "v_195": 121.45008369862578,
    "v_22": 137.34136944089184,
    "v_88": 122.16776139125326,
    "v_61": 133.8291592128801,
    "v_31": 151.92832984354035,
    "v_141": 212.40193070779742,
    "v_183": 197.45380455431186,
    "v_21": 185.39179677790355,
    "v_39": 171.25080591048243,
    "v_4": 190.21903571506766,
    "v_36": 161.40235378665233,
    "v_3": 238.30424318863334,
    "v_87": 242.5437014054976,
    "v_110": 238.29762985687438,
    "v_62": 190.23416158907642,
    "v_127": 191.52145091120775,
    "v_14": 256.1521486867813,
    "v_179": 178.7234075299021,
    "v_161": 234.39624329159216,
    "v_169": 158.8992202985121,
    "v_149": 232.89656398150044,
    "v_168": 188.78054571376688,
    "v_1": 192.85658013190786,
    "v_107": 172.766953098135,
    "v_165": 237.9610129937369,
    "v_49": 155.30321102039923,
    "v_47": 206.34361150929033,
    "v_0": 203.53445484647452,
    "v_89": 287.9245000650395,
    "v_64": 213.89982110912342,
    "v_24": 272.19230769230774,
    "v_86": 256.92449362548314,
    "v_131": 276.7267342047341,
    "v_180": 251.09079967699185,
    "v_187": 233.01978401087965,
    "v_6": 224.40591486133704,
    "v_163": 208.24280282979865,
    "v_30": 264.09939262104115,
    "v_160": 245.1903721309048,
    "v_40": 250.43318509474523,
    "v_146": 189.4221373917993,
    "v_77": 219.63740661033344,
    "v_54": 250.33777276350986,
    "v_72": 235.83415695259586,
    "v_117": 252.83642238853452,
    "v_8": 307.2014814872416,
    "v_97": 219.44775816848426,
    "v_52": 272.9962389861272,
    "v_53": 224.17599500805588,
    "v_38": 261.93049915577416,
    "v_122": 316.3251911582315,
    "v_85": 198.61408109783224,
    "v_133": 273.5027599938695,
    "v_139": 238.40509381789704,
    "v_48": 230.24205369834112,
    "v_63": 214.8325702459009,
    "v_68": 304.7943939797875,
    "v_19": 280.20966358469497,
    "v_116": 244.29415893597923,
    "v_120": 206.32995741702243,
    "v_25": 359.2957979161065,
    "v_99": 278.0478227215884,
    "v_118": 295.0890899747698,
    "v_176": 262.8209249521219,
    "v_58": 293.00926728674364,
    "v_71": 324.2468578184586,
    "v_140": 321.25508113197094,
    "v_147": 283.22123417961984,
    "v_167": 351.805481607983,
    "v_138": 279.5778060461745,
    "v_90": 338.70439378275967,
    "v_10": 363.68529308353004,
    "v_125": 327.8125876584614,
    "v_100": 332.4253545941727,
    "v_143": 343.0765090134471,
    "v_186": 360.4587153600163,
    "v_115": 272.9599362999082,
    "v_191": 379.34097901863737,
    "v_173": 444.4156978354075,
    "v_198": 356.47630050061105,
    "v_29": 329.27638640429336,
    "v_177": 409.99270720238627,
    "v_33": 389.3299071369251,
    "v_50": 414.0382361539878,
    "v_41": 390.4113015502588,
    "v_23": 337.2459788190111,
    "v_74": 396.44753757919057,
    "v_46": 415.62273730087276,
    "v_189": 334.13190161673333,
    "v_196": 389.12724591954486,
    "v_45": 468.0258161815749,
    "v_142": 498.1614345270983
  },
  "total_rerouting_events": 0,
  "vehicle_reroutes": {},
  "congestion_levels_over_time": [
    1.0,
    1.0,
    1.0,
    1.0,
    1.0,
    1.0,
    1.0,
    1.0,
    1.0,
    1.0,
    1.0,
    1.0,
    1.0,
    1.0,
    1.0,
    1.0,
    1.0,
    1.0,
    1.0,
    1.0,
    1.0,
    1.0,
    1.0,
    1.0,
    1.0,
    1.0,
    1.0,
    1.0,
    1.0,
    1.0,
    1.0,
    1.0,
    1.0,
    1.0,
    1.0,
    1.0,
    1.0,
    1.0,
    1.0,
    1.0,
    1.0,
    1.0,
    1.0,
    1.0,
    1.0,
    1.0,
    1.0,
    1.0,
    1.0,
    1.0,
    1.0,
    1.0,
    1.0,
    1.0,
    1.0,
    1.0,
    1.0,
    1.0,
    1.0,
    1.0,
    1.0,
    1.0,
    1.0,
    1.0,
    1.0,
    1.0,
    1.0,
    1.0,
    1.0,
    1.0,
    1.0,
    1.0,
    1.0,
    1.0,
    1.0,
    1.0,
    1.0,
    1.0,
    1.0,
    1.0,
    1.0,
    1.0,
    1.0,
    1.0,
    1.0,
    1.0,
    1.0,
    1.0,
    1.0,
    1.0,
    1.0,
    1.0,
    1.0,
    1.0,
    1.0,
    1.0,
    1.0,
    1.0,
    1.0,
    1.0,
    1.0,
    1.0,
    1.0,
    1.0,
    1.0,
    1.0,
    1.0,
    1.0,
    1.0,
    1.0,
    1.0,
    1.0,
    1.0,
    1.0,
    1.0,
    1.0,
    1.0,
    1.0,
    1.0,
    1.0,
    1.0,
    1.0,
    1.0,
    1.0,
    1.0,
    1.0,
    1.0,
    1.0,
    1.0,
    1.0,
    1.0,
    1.0,
    1.0,
    1.0,
    1.0,
    1.0,
    1.0,
    1.0,
    1.0,
    1.0,
    1.0,
    1.0,
    1.0,
    1.0,
    1.0,
    1.0,
    1.0,
    1.0,
    1.0,
    1.0,
    1.0,
    1.0,
    1.0,
    1.0,
    1.0,
    1.0,
    1.0,
    1.0,
    1.0,
    1.0,
    1.0,
    1.0,
    1.0,
    1.0,
    1.0,
    1.0,
    1.0,
    1.0,
    1.0,
    1.0,
    1.0,
    1.0,
    1.0,
    1.0,
    1.0,
    1.0,
    1.0,
    1.0,
    1.0,
    1.0,
    1.0,
    1.0,
    1.0,
    1.0,
    1.0,
    1.0,
    1.0,
    1.0,
    1.0,
    1.0,
    1.0,
    1.0,
    1.0,
    1.0,
    1.0,
    1.0,
    1.0,
    1.0,
    1.0,
    1.0,
    1.0,
    1.0,
    1.0,
    1.0,
    1.0,
    1.0,
    1.0,
    1.0,
    1.0,
    1.0,
    1.0,
    1.0,
    1.0,
    1.0,
    1.0,
    1.0,
    1.0,
    1.0,
    1.0,
    1.0,
    1.0,
    1.0,
    1.0,
    1.0,
    1.0,
    1.0,
    1.0,
    1.0,
    1.0,
    1.0,
    1.0,
    1.0,
    1.0,
    1.0,
    1.0,
    1.0,
    1.0,
    1.0,
    1.0,
    1.0,
    1.0,
    1.0,
    1.0,
    1.0,
    1.0,
    1.0,
    1.0,
    1.0,
    1.0,
    1.0,
    1.0,
    1.0,
    1.0,
    1.0,
    1.0,
    1.0,
    1.0,
    1.0,
    1.0,
    1.0,
    1.0,
    1.0,
    1.0,
    1.0,
    1.0,
    1.0,
    1.0,
    1.0,
    1.0,
    1.0,
    1.0,
    1.0,
    1.0,
    1.0,
    1.0,
    1.0,
    1.0,
    1.0,
    1.0,
    1.0,
    1.0,
    1.0,
    1.0,
    1.0,
    1.0,
    1.0,
    1.0,
    1.0,
    1.0,
    1.0,
    1.0,
    1.0,
    1.0,
    1.0,
    1.0,
    1.0,
    1.0,
    1.0,
    1.0,
    1.0,
    1.0,
    1.0,
    1.0,
    1.0,
    1.0,
    1.0,
    1.0,
    1.0,
    1.0,
    1.0,
    1.0,
    1.0,
    1.0,
    1.0,
    1.0,
    1.0,
    1.0,
    1.0,
    1.0,
    1.0,
    1.0,
    1.0,
    1.0,
    1.0,
    1.0,
    1.0,
    1.0,
    1.0,
    1.0,
    1.0,
    1.0,
    1.0,
    1.0,
    1.0,
    1.0,
    1.0,
    1.0,
    1.0,
    1.0,
    1.0,
    1.0,
    1.0,
    1.0,
    1.0,
    1.0,
    1.0,
    1.0,
    1.0,
    1.0,
    1.0,
    1.0,
    1.0,
    1.0,
    1.0,
    1.0,
    1.0,
    1.0,
    1.0,
    1.0,
    1.0,
    1.0,
    1.0,
    1.0,
    1.0,
    1.0,
    1.0,
    1.0,
    1.0,
    1.0,
    1.0,
    1.0,
    1.0,
    1.0,
    1.0,
    1.0,
    1.0,
    1.0,
    1.0,
    1.0,
    1.0,
    1.0,
    1.0,
    1.0,
    1.0,
    1.0,
    1.0,
    1.0,
    1.0,
    1.0,
    1.0,
    1.0,
    1.0,
    1.0,
    1.0,
    1.0,
    1.0,
    1.0,
    1.0,
    1.0,
    1.0,
    1.0,
    1.0,
    1.0,
    1.0,
    1.0,
    1.0,
    1.0,
    1.0,
    1.0,
    1.0,
    1.0,
    1.0,
    1.0,
    1.0,
    1.0,
    1.0,
    1.0,
    1.0,
    1.0,
    1.0,
    1.0,
    1.0,
    1.0,
    1.0,
    1.0,
    1.0,
    1.0,
    1.0,
    1.0,
    1.0,
    1.0,
    1.0,
    1.0,
    1.0,
    1.0,
    1.0,
    1.0,
    1.0,
    1.0,
    1.0,
    1.0,
    1.0,
    1.0,
    1.0,
    1.0,
    1.0,
    1.0,
    1.0,
    1.0,
    1.0,
    1.0,
    1.0,
    1.0,
    1.0,
    1.0,
    1.0,
    1.0,
    1.0,
    1.0,
    1.0,
    1.0,
    1.0,
    1.0,
    1.0,
    1.0,
    1.0,
    1.0,
    1.0,
    1.0,
    1.0,
    1.0,
    1.0,
    1.0,
    1.0,
    1.0,
    1.0,
    1.0,
    1.0,
    1.0,
    1.0,
    1.0,
    1.0,
    1.0,
    1.0,
    1.0,
    1.0,
    1.0,
    1.0,
    1.0,
    1.0,
    1.0,
    1.0,
    1.0,
    1.0,
    1.0,
    1.0,
    1.0,
    1.0,
    1.0,
    1.0,
    1.0,
    1.0,
    1.0,
    1.0,
    1.0,
    1.0,
    1.0,
    1.0,
    1.0,
    1.0,
    1.0,
    1.0,
    1.0,
    1.0,
    1.0,
    1.0,
    1.0,
    1.0,
    1.0,
    1.0,
    1.0,
    1.0,
    1.0,
    1.0,
    1.0,
    1.0,
    1.0,
    1.0,
    1.0,
    1.0,
    1.0,
    1.0,
    1.0,
    1.0,
    1.0,
    1.0,
    1.0,
    1.0,
    1.0,
    1.0,
    1.0,
    1.0,
    1.0,
    1.0,
    1.0,
    1.0,
    1.0,
    1.0,
    1.0,
    1.0,
    1.0,
    1.0,
    1.0,
    1.0,
    1.0,
    1.0,
    1.0,
    1.0,
    1.0,
    1.0,
    1.0,
    1.0,
    1.0,
    1.0,
    1.0,
    1.0,
    1.0,
    1.0,
    1.0,
    1.0,
    1.0,
    1.0,
    1.0,
    1.0,
    1.0,
    1.0,
    1.0,
    1.0,
    1.0,
    1.0,
    1.0,
    1.0,
    1.0,
    1.0,
    1.0,
    1.0,
    1.0,
    1.0,
    1.0,
    1.0,
    1.0,
    1.0,
    1.0,
    1.0,
    1.0,
    1.0,
    1.0,
    1.0,
    1.0,
    1.0
  ],
  "throughput_over_time": [
    28,
    0,
    0,
    0,
    0,
    0,
    0,
    0,
    0,
    0,
    0,
    0,
    1,
    0,
    0,
    0,
    0,
    0,
    0,
    0,
    0,
    0,
    0,
    0,
    0,
    0,
    0,
    0,
    0,
    0,
    0,
    0,
    0,
    0,
    0,
    0,
    0,
    0,
    0,
    0,
    0,
    0,
    0,
    0,
    0,
    0,
    0,
    0,
    0,
    0,
    1,
    0,
    0,
    0,
    0,
    0,
    0,
    0,
    0,
    0,
    0,
    0,
    0,
    0,
    0,
    0,
    0,
    0,
    1,
    0,
    0,
    0,
    0,
    0,
    0,
    0,
    0,
    0,
    0,
    1,
    0,
    0,
    0,
    0,
    0,
    0,
    1,
    0,
    0,
    0,
    0,
    0,
    0,
    0,
    0,
    0,
    0,
    0,
    0,
    0,
    1,
    0,
    0,
    0,
    0,
    1,
    1,
    0,
    1,
    0,
    2,
    0,
    0,
    0,
    0,
    1,
    0,
    0,
    1,
    0,
    0,
    0,
    0,
    0,
    0,
    0,
    0,
    0,
    0,
    0,
    1,
    0,
    1,
    0,
    0,
    0,
    0,
    0,
    0,
    0,
    0,
    1,
    1,
    0,
    0,
    0,
    0,
    0,
    1,
    0,
    1,
    1,
    2,
    0,
    1,
    0,
    0,
    0,
    0,
    0,
    1,
    0,
    0,
    1,
    0,
    0,
    0,
    0,
    0,
    0,
    0,
    0,
    0,
    0,
    0,
    0,
    0,
    0,
    0,
    1,
    0,
    0,
    0,
    0,
    1,
    1,
    0,
    1,
    1,
    0,
    0,
    0,
    1,
    0,
    0,
    0,
    0,
    1,
    0,
    0,
    0,
    0,
    0,
    2,
    0,
    0,
    2,
    0,
    0,
    0,
    1,
    1,
    1,
    0,
    0,
    1,
    0,
    0,
    0,
    0,
    0,
    0,
    0,
    0,
    1,
    0,
    0,
    0,
    0,
    0,
    0,
    1,
    1,
    2,
    4,
    1,
    1,
    0,
    0,
    2,
    0,
    0,
    1,
    0,
    0,
    0,
    0,
    0,
    0,
    0,
    0,
    0,
    0,
    1,
    0,
    0,
    0,
    0,
    0,
    0,
    0,
    0,
    0,
    0,
    0,
    0,
    1,
    1,
    0,
    0,
    0,
    0,
    0,
    0,
    0,
    0,
    0,
    0,
    0,
    0,
    2,
    0,
    0,
    0,
    1,
    2,
    1,
    0,
    0,
    0,
    1,
    0,
    1,
    2,
    0,
    1,
    0,
    0,
    1,
    1,
    0,
    0,
    0,
    0,
    0,
    0,
    1,
    0,
    0,
    0,
    0,
    0,
    0,
    0,
    0,
    1,
    0,
    1,
    0,
    0,
    0,
    0,
    2,
    2,
    2,
    2,
    0,
    0,
    2,
    0,
    0,
    2,
    1,
    0,
    0,
    0,
    0,
    0,
    0,
    0,
    0,
    0,
    1,
    0,
    0,
    0,
    0,
    0,
    0,
    0,
    0,
    0,
    0,
    1,
    0,
    0,
    0,
    0,
    0,
    0,
    1,
    0,
    0,
    1,
    0,
    0,
    1,
    1,
    1,
    3,
    2,
    1,
    0,
    0,
    0,
    0,
    1,
    2,
    0,
    1,
    1,
    2,
    0,
    2,
    0,
    0,
    0,
    0,
    0,
    0,
    0,
    0,
    1,
    1,
    0,
    0,
    0,
    0,
    0,
    0,
    1,
    0,
    0,
    0,
    0,
    0,
    0,
    1,
    0,
    1,
    1,
    0,
    0,
    1,
    1,
    2,
    0,
    0,
    0,
    0,
    0,
    1,
    0,
    0,
    0,
    0,
    0,
    1,
    0,
    0,
    0,
    1,
    0,
    0,
    0,
    0,
    0,
    0,
    0,
    0,
    0,
    0,
    0,
    0,
    0,
    0,
    0,
    0,
    0,
    0,
    0,
    0,
    0,
    0,
    0,
    0,
    1,
    0,
    0,
    3,
    0,
    0,
    1,
    1,
    2,
    0,
    0,
    0,
    0,
    0,
    0,
    0,
    0,
    0,
    1,
    0,
    0,
    1,
    0,
    1,
    1,
    0,
    0,
    0,
    0,
    0,
    0,
    1,
    0,
    0,
    0,
    0,
    0,
    0,
    0,
    0,
    0,
    0,
    0,
    0,
    0,
    0,
    0,
    0,
    2,
    0,
    0,
    1,
    0,
    0,
    0,
    0,
    0,
    0,
    0,
    1,
    1,
    0,
    0,
    1,
    0,
    0,
    0,
    0,
    0,
    0,
    0,
    0,
    0,
    0,
    0,
    0,
    0,
    0,
    0,
    0,
    0,
    0,
    0,
    0,
    0,
    0,
    0,
    0,
    0,
    0,
    0,
    0,
    1,
    0,
    2,
    0,
    0,
    0,
    0,
    0,
    0,
    0,
    0,
    0,
    0,
    0,
    0,
    1,
    0,
    0,
    0,
    1,
    1,
    0,
    1,
    0,
    0,
    0,
    0,
    1,
    0,
    0,
    0,
    0,
    0,
    0,
    0,
    0,
    1,
    0,
    0,
    0,
    0,
    0,
    1,
    0,
    1,
    1,
    1,
    0,
    0,
    0,
    0,
    0
  ],
  "ambulance_travel_times": {},
  "ambulance_response_times": {},
  "ambulance_success_rate": 1.0,
  "emergency_corridor_activation_time": 0.0,
  "emergency_corridor_activation_count": 0,
  "packets_sent": 0,
  "packets_delivered": 0,
  "packet_delivery_ratio": 1.0,
  "message_latencies": [],
  "packet_loss_count": 0,
  "communication_overhead_per_vehicle": {},
  "vehicle_energy_consumed": {
    "v_42": 0.0,
    "v_55": 0.0,
    "v_59": 0.0,
    "v_67": 0.0,
    "v_76": 0.0,
    "v_82": 0.0,
    "v_92": 0.0,
    "v_95": 0.0,
    "v_108": 0.0,
    "v_123": 0.0,
    "v_130": 0.0,
    "v_134": 0.0,
    "v_136": 0.0,
    "v_145": 0.0,
    "v_152": 0.0,
    "v_156": 0.0,
    "v_157": 0.0,
    "v_158": 0.0,
    "v_159": 0.0,
    "v_166": 0.0,
    "v_170": 0.0,
    "v_178": 0.0,
    "v_181": 0.0,
    "v_184": 0.0,
    "v_185": 0.0,
    "v_188": 0.0,
    "v_194": 0.0,
    "v_199": 0.0,
    "v_148": 0.1366541662239702,
    "v_34": 0.07654488651064698,
    "v_174": 0.13784780538033012,
    "v_27": 0.2773641584859911,
    "v_164": 0.4446869219888733,
    "v_129": 0.14193056659253014,
    "v_43": 0.1359467785999356,
    "v_5": 0.1139142475061064,
    "v_135": 0.10533361066884671,
    "v_151": 0.07501213299359058,
    "v_197": 0.34119526558729485,
    "v_56": 0.14738432677131827,
    "v_106": 0.13336240323409856,
    "v_75": 0.4057254275425304,
    "v_193": 0.18126790543049737,
    "v_32": 0.09648759111526399,
    "v_11": 0.33679476538063524,
    "v_109": 0.42823852632435105,
    "v_119": 0.2185446095618595,
    "v_144": 0.30553921539534695,
    "v_93": 0.34393851538357173,
    "v_124": 0.15508200883178205,
    "v_112": 0.29564449238215984,
    "v_113": 0.35690278598956754,
    "v_83": 0.2246340061691649,
    "v_20": 0.4657177675449112,
    "v_94": 0.16666155065744123,
    "v_96": 0.1267047821448867,
    "v_155": 0.40849781777640254,
    "v_79": 0.17435829524805926,
    "v_172": 0.5740019674665973,
    "v_81": 0.34786303407846686,
    "v_9": 0.2429954425306359,
    "v_12": 0.37271176418191637,
    "v_98": 0.1646872459828777,
    "v_121": 0.4063647697684802,
    "v_65": 0.19534423628855463,
    "v_28": 0.2104001258886072,
    "v_66": 0.22605937788861447,
    "v_44": 0.5236028477561103,
    "v_102": 0.5824901026352105,
    "v_111": 0.21508222607009003,
    "v_69": 0.21704922009590505,
    "v_17": 0.32014184779500854,
    "v_91": 0.24989548951082527,
    "v_60": 0.22461243755360089,
    "v_103": 0.5376402409335048,
    "v_132": 0.25647840261536065,
    "v_137": 0.17178451916735565,
    "v_2": 0.2662022111558776,
    "v_16": 0.39838345289047505,
    "v_101": 0.23779650904314667,
    "v_175": 0.27731852860115663,
    "v_162": 0.323834617460094,
    "v_126": 0.28751941562092764,
    "v_13": 0.18885996789289147,
    "v_150": 0.5791572263025597,
    "v_15": 0.17361704507861028,
    "v_35": 0.25904092171371446,
    "v_80": 0.4060248997429219,
    "v_84": 0.23607067284738734,
    "v_195": 0.33390618300603625,
    "v_22": 0.41121552700300895,
    "v_88": 0.2840564564413086,
    "v_61": 0.29565607103542946,
    "v_31": 0.7010504196838041,
    "v_141": 0.4614658417856758,
    "v_183": 0.34985024159735073,
    "v_21": 0.3479091803038161,
    "v_39": 0.5480177896339483,
    "v_4": 0.3977532528064327,
    "v_36": 0.32797778548972933,
    "v_3": 0.15827164919103162,
    "v_87": 0.6238005364300133,
    "v_110": 0.22487232930927728,
    "v_62": 0.5027182458561199,
    "v_127": 0.7835432267649627,
    "v_14": 0.3054041608676363,
    "v_179": 0.47719786052790303,
    "v_161": 0.20092654828517417,
    "v_169": 0.38356468096846646,
    "v_149": 0.47433969633602535,
    "v_168": 0.2775504545410826,
    "v_1": 0.28451926338518674,
    "v_107": 0.5636762743880555,
    "v_165": 0.2771759695535125,
    "v_49": 0.5331811139424211,
    "v_47": 0.3136171916246151,
    "v_0": 0.39796858881931785,
    "v_89": 0.6493204789362735,
    "v_64": 0.2708563083747479,
    "v_24": 0.2875214161445866,
    "v_86": 0.5505513262944366,
    "v_131": 0.6382525984518639,
    "v_180": 0.42030776621427896,
    "v_187": 0.5161410261274145,
    "v_6": 0.44617598287298016,
    "v_163": 0.4504301351185101,
    "v_30": 0.5045856345155502,
    "v_160": 0.5972116245167354,
    "v_40": 0.6215048816716993,
    "v_146": 0.40096230620388196,
    "v_77": 0.6427598167871064,
    "v_54": 0.2732269125392901,
    "v_72": 0.5273128680573902,
    "v_117": 0.4071605186590608,
    "v_8": 0.8878955455271815,
    "v_97": 0.811477925845905,
    "v_52": 0.8393478233414612,
    "v_53": 0.5923460292073326,
    "v_38": 0.3691325072265528,
    "v_122": 0.40662334150387647,
    "v_85": 0.5075194040030342,
    "v_133": 0.5585886654011747,
    "v_139": 0.3845858577106646,
    "v_48": 0.626498523834175,
    "v_63": 0.39249387533711083,
    "v_68": 0.808732645974684,
    "v_19": 0.3784766474494917,
    "v_116": 0.4669299598664232,
    "v_120": 0.4729407685658834,
    "v_25": 0.32289652227791477,
    "v_99": 0.7297004681902597,
    "v_118": 0.44595716422124854,
    "v_176": 0.4634124852653187,
    "v_58": 0.7465866322892256,
    "v_71": 0.8668377280991317,
    "v_140": 0.4166966572731941,
    "v_147": 0.4611436006214029,
    "v_167": 0.864486844553498,
    "v_138": 0.4685748543072899,
    "v_90": 1.0012170398574882,
    "v_10": 0.6452588265358433,
    "v_125": 0.6927820963965173,
    "v_100": 1.0592968832076268,
    "v_143": 0.4724828501603894,
    "v_186": 0.7436172913184016,
    "v_115": 0.567137587169796,
    "v_191": 0.351512434281409,
    "v_173": 0.6136091358601496,
    "v_198": 0.8775942801657428,
    "v_29": 0.5191636813445794,
    "v_177": 0.6079761116783959,
    "v_33": 0.4318213450342941,
    "v_50": 1.0497189498541735,
    "v_41": 1.1127576507738814,
    "v_23": 0.5138847192690907,
    "v_74": 0.5244766213924551,
    "v_46": 0.7197298096223692,
    "v_189": 0.607808044501533,
    "v_196": 0.6886895456217824,
    "v_45": 0.7425622906063237,
    "v_142": 0.5142101326132079
  },
  "vehicle_travelled_distance": {
    "v_42": 2704.0,
    "v_55": 2062.64,
    "v_59": 3888.95,
    "v_67": 2402.37,
    "v_76": 938.31,
    "v_82": 699.91,
    "v_92": 567.4,
    "v_95": 3354.31,
    "v_108": 2938.49,
    "v_123": 4194.13,
    "v_130": 2161.27,
    "v_134": 3773.48,
    "v_136": 2240.61,
    "v_145": 2018.0,
    "v_152": 803.81,
    "v_156": 1569.1,
    "v_157": 1066.78,
    "v_158": 1311.5,
    "v_159": 2252.52,
    "v_166": 1424.8999999999999,
    "v_170": 1006.29,
    "v_178": 13485.41,
    "v_181": 1257.31,
    "v_184": 3666.9,
    "v_185": 2828.0,
    "v_188": 1435.41,
    "v_194": 454.92,
    "v_199": 2155.35,
    "v_148": 157.32,
    "v_34": 312.12,
    "v_174": 397.22,
    "v_27": 818.12,
    "v_164": 1451.12,
    "v_129": 582.14,
    "v_43": 1138.08,
    "v_5": 636.02,
    "v_135": 543.0,
    "v_151": 311.79,
    "v_197": 788.31,
    "v_56": 1107.76,
    "v_106": 770.99,
    "v_75": 1584.9099999999999,
    "v_193": 782.57,
    "v_32": 609.71,
    "v_11": 1443.25,
    "v_109": 1528.3799999999999,
    "v_119": 1015.2,
    "v_144": 1273.45,
    "v_93": 1218.17,
    "v_124": 859.72,
    "v_112": 1350.82,
    "v_113": 1165.22,
    "v_83": 1121.87,
    "v_20": 2190.46,
    "v_94": 539.32,
    "v_96": 526.18,
    "v_155": 2255.17,
    "v_79": 716.63,
    "v_172": 1396.94,
    "v_81": 1424.41,
    "v_9": 1117.6100000000001,
    "v_12": 1360.94,
    "v_98": 784.25,
    "v_121": 1471.57,
    "v_65": 1027.01,
    "v_28": 1486.89,
    "v_66": 989.22,
    "v_44": 2093.71,
    "v_102": 1923.07,
    "v_111": 1604.45,
    "v_69": 1454.61,
    "v_17": 1808.22,
    "v_91": 1377.71,
    "v_60": 1681.08,
    "v_103": 1949.3,
    "v_132": 1558.64,
    "v_137": 687.53,
    "v_2": 733.2,
    "v_16": 1505.61,
    "v_101": 1111.21,
    "v_175": 1093.17,
    "v_162": 1269.05,
    "v_126": 1521.9099999999999,
    "v_13": 750.27,
    "v_150": 1649.55,
    "v_15": 557.87,
    "v_35": 1675.59,
    "v_80": 1747.3799999999999,
    "v_84": 1226.35,
    "v_195": 1776.19,
    "v_22": 1960.21,
    "v_88": 1990.6,
    "v_61": 1768.35,
    "v_31": 2513.75,
    "v_141": 1329.3700000000001,
    "v_183": 1476.46,
    "v_21": 1616.52,
    "v_39": 2200.63,
    "v_4": 1789.79,
    "v_36": 1906.11,
    "v_3": 843.62,
    "v_87": 1823.15,
    "v_110": 973.02,
    "v_62": 1924.24,
    "v_127": 2545.34,
    "v_14": 899.55,
    "v_179": 2175.47,
    "v_161": 1012.95,
    "v_169": 2007.52,
    "v_149": 1342.1399999999999,
    "v_168": 1719.91,
    "v_1": 1582.6,
    "v_107": 2398.25,
    "v_165": 1144.09,
    "v_49": 2907.5299999999997,
    "v_47": 1656.81,
    "v_0": 1934.52,
    "v_89": 1773.36,
    "v_64": 1700.48,
    "v_24": 1059.95,
    "v_86": 1749.1399999999999,
    "v_131": 1802.81,
    "v_180": 1668.53,
    "v_187": 2257.37,
    "v_6": 2261.44,
    "v_163": 2437.65,
    "v_30": 1735.33,
    "v_160": 2283.85,
    "v_40": 1910.12,
    "v_146": 2363.82,
    "v_77": 2891.42,
    "v_54": 1643.38,
    "v_72": 2318.72,
    "v_117": 2006.74,
    "v_8": 2066.38,
    "v_97": 2936.31,
    "v_52": 2797.12,
    "v_53": 2520.35,
    "v_38": 1801.49,
    "v_122": 1383.27,
    "v_85": 2798.48,
    "v_133": 2140.54,
    "v_139": 2062.39,
    "v_48": 2723.37,
    "v_63": 2345.31,
    "v_68": 2378.64,
    "v_19": 1610.46,
    "v_116": 2279.35,
    "v_120": 2679.68,
    "v_25": 1160.48,
    "v_99": 3092.12,
    "v_118": 2036.57,
    "v_176": 2287.25,
    "v_58": 2749.72,
    "v_71": 3004.28,
    "v_140": 1829.8,
    "v_147": 2219.12,
    "v_167": 2566.88,
    "v_138": 2364.54,
    "v_90": 3113.49,
    "v_10": 2064.88,
    "v_125": 2578.29,
    "v_100": 3447.49,
    "v_143": 2070.98,
    "v_186": 2217.76,
    "v_115": 2998.69,
    "v_191": 1666.51,
    "v_173": 1654.89,
    "v_198": 3420.63,
    "v_29": 2467.69,
    "v_177": 2126.13,
    "v_33": 2032.92,
    "v_50": 3251.11,
    "v_41": 3807.45,
    "v_23": 2790.15,
    "v_74": 2322.62,
    "v_46": 3333.99,
    "v_189": 3028.25,
    "v_196": 2999.7599999999998,
    "v_45": 2229.5,
    "v_142": 1356.4
  },
  "charging_queue_lengths_over_time": [
    0.0,
    0.0,
    0.0,
    0.0,
    0.0,
    0.0,
    0.0,
    0.0,
    0.0,
    0.0,
    0.0,
    0.0,
    0.0,
    0.0,
    0.0,
    0.0,
    0.0,
    0.0,
    0.0,
    0.0,
    0.0,
    0.0,
    0.0,
    0.0,
    0.0,
    0.0,
    0.0,
    0.0,
    0.0,
    0.0,
    0.0,
    0.0,
    0.0,
    0.0,
    0.0,
    0.0,
    0.0,
    0.0,
    0.0,
    0.0,
    0.0,
    0.0,
    0.0,
    0.0,
    0.0,
    0.0,
    0.0,
    0.0,
    0.0,
    0.0,
    0.0,
    0.0,
    0.0,
    0.0,
    0.0,
    0.0,
    0.0,
    0.0,
    0.0,
    0.0,
    0.0,
    0.0,
    0.0,
    0.0,
    0.0,
    0.0,
    0.0,
    0.0,
    0.0,
    0.0,
    0.0,
    0.0,
    0.0,
    0.0,
    0.0,
    0.0,
    0.0,
    0.0,
    0.0,
    0.0,
    0.0,
    0.0,
    0.0,
    0.0,
    0.0,
    0.0,
    0.0,
    0.0,
    0.0,
    0.0,
    0.0,
    0.0,
    0.0,
    0.0,
    0.0,
    0.0,
    0.0,
    0.0,
    0.0,
    0.0,
    0.0,
    0.0,
    0.0,
    0.0,
    0.0,
    0.0,
    0.0,
    0.0,
    0.0,
    0.0,
    0.0,
    0.0,
    0.0,
    0.0,
    0.0,
    0.0,
    0.0,
    0.0,
    0.0,
    0.0,
    0.0,
    0.0,
    0.0,
    0.0,
    0.0,
    0.0,
    0.0,
    0.0,
    0.0,
    0.0,
    0.0,
    0.0,
    0.0,
    0.0,
    0.0,
    0.0,
    0.0,
    0.0,
    0.0,
    0.0,
    0.0,
    0.0,
    0.0,
    0.0,
    0.0,
    0.0,
    0.0,
    0.0,
    0.0,
    0.0,
    0.0,
    0.0,
    0.0,
    0.0,
    0.0,
    0.0,
    0.0,
    0.0,
    0.0,
    0.0,
    0.0,
    0.0,
    0.0,
    0.0,
    0.0,
    0.0,
    0.0,
    0.0,
    0.0,
    0.0,
    0.0,
    0.0,
    0.0,
    0.0,
    0.0,
    0.0,
    0.0,
    0.0,
    0.0,
    0.0,
    0.0,
    0.0,
    0.0,
    0.0,
    0.0,
    0.0,
    0.0,
    0.0,
    0.0,
    0.0,
    0.0,
    0.0,
    0.0,
    0.0,
    0.0,
    0.0,
    0.0,
    0.0,
    0.0,
    0.0,
    0.0,
    0.0,
    0.0,
    0.0,
    0.0,
    0.0,
    0.0,
    0.0,
    0.0,
    0.0,
    0.0,
    0.0,
    0.0,
    0.0,
    0.0,
    0.0,
    0.0,
    0.0,
    0.0,
    0.0,
    0.0,
    0.0,
    0.0,
    0.0,
    0.0,
    0.0,
    0.0,
    0.0,
    0.0,
    0.0,
    0.0,
    0.0,
    0.0,
    0.0,
    0.0,
    0.0,
    0.0,
    0.0,
    0.0,
    0.0,
    0.0,
    0.0,
    0.0,
    0.0,
    0.0,
    0.0,
    0.0,
    0.0,
    0.0,
    0.0,
    0.0,
    0.0,
    0.0,
    0.0,
    0.0,
    0.0,
    0.0,
    0.0,
    0.0,
    0.0,
    0.0,
    0.0,
    0.0,
    0.0,
    0.0,
    0.0,
    0.0,
    0.0,
    0.0,
    0.0,
    0.0,
    0.0,
    0.0,
    0.0,
    0.0,
    0.0,
    0.0,
    0.0,
    0.0,
    0.0,
    0.0,
    0.0,
    0.0,
    0.0,
    0.0,
    0.0,
    0.0,
    0.0,
    0.0,
    0.0,
    0.0,
    0.0,
    0.0,
    0.0,
    0.0,
    0.0,
    0.0,
    0.0,
    0.0,
    0.0,
    0.0,
    0.0,
    0.0,
    0.0,
    0.0,
    0.0,
    0.0,
    0.0,
    0.0,
    0.0,
    0.0,
    0.0,
    0.0,
    0.0,
    0.0,
    0.0,
    0.0,
    0.0,
    0.0,
    0.0,
    0.0,
    0.0,
    0.0,
    0.0,
    0.0,
    0.0,
    0.0,
    0.0,
    0.0,
    0.0,
    0.0,
    0.0,
    0.0,
    0.0,
    0.0,
    0.0,
    0.0,
    0.0,
    0.0,
    0.0,
    0.0,
    0.0,
    0.0,
    0.0,
    0.0,
    0.0,
    0.0,
    0.0,
    0.0,
    0.0,
    0.0,
    0.0,
    0.0,
    0.0,
    0.0,
    0.0,
    0.0,
    0.0,
    0.0,
    0.0,
    0.0,
    0.0,
    0.0,
    0.0,
    0.0,
    0.0,
    0.0,
    0.0,
    0.0,
    0.0,
    0.0,
    0.0,
    0.0,
    0.0,
    0.0,
    0.0,
    0.0,
    0.0,
    0.0,
    0.0,
    0.0,
    0.0,
    0.0,
    0.0,
    0.0,
    0.0,
    0.0,
    0.0,
    0.0,
    0.0,
    0.0,
    0.0,
    0.0,
    0.0,
    0.0,
    0.0,
    0.0,
    0.0,
    0.0,
    0.0,
    0.0,
    0.0,
    0.0,
    0.0,
    0.0,
    0.0,
    0.0,
    0.0,
    0.0,
    0.0,
    0.0,
    0.0,
    0.0,
    0.0,
    0.0,
    0.0,
    0.0,
    0.0,
    0.0,
    0.0,
    0.0,
    0.0,
    0.0,
    0.0,
    0.0,
    0.0,
    0.0,
    0.0,
    0.0,
    0.0,
    0.0,
    0.0,
    0.0,
    0.0,
    0.0,
    0.0,
    0.0,
    0.0,
    0.0,
    0.0,
    0.0,
    0.0,
    0.0,
    0.0,
    0.0,
    0.0,
    0.0,
    0.0,
    0.0,
    0.0,
    0.0,
    0.0,
    0.0,
    0.0,
    0.0,
    0.0,
    0.0,
    0.0,
    0.0,
    0.0,
    0.0,
    0.0,
    0.0,
    0.0,
    0.0,
    0.0,
    0.0,
    0.0,
    0.0,
    0.0,
    0.0,
    0.0,
    0.0,
    0.0,
    0.0,
    0.0,
    0.0,
    0.0,
    0.0,
    0.0,
    0.0,
    0.0,
    0.0,
    0.0,
    0.0,
    0.0,
    0.0,
    0.0,
    0.0,
    0.0,
    0.0,
    0.0,
    0.0,
    0.0,
    0.0,
    0.0,
    0.0,
    0.0,
    0.0,
    0.0,
    0.0,
    0.0,
    0.0,
    0.0,
    0.0,
    0.0,
    0.0,
    0.0,
    0.0,
    0.0,
    0.0,
    0.0,
    0.0,
    0.0,
    0.0,
    0.0,
    0.0,
    0.0,
    0.0,
    0.0,
    0.0,
    0.0,
    0.0,
    0.0,
    0.0,
    0.0,
    0.0,
    0.0,
    0.0,
    0.0,
    0.0,
    0.0,
    0.0,
    0.0,
    0.0,
    0.0,
    0.0,
    0.0,
    0.0,
    0.0,
    0.0,
    0.0,
    0.0,
    0.0,
    0.0,
    0.0,
    0.0,
    0.0,
    0.0,
    0.0,
    0.0,
    0.0,
    0.0,
    0.0,
    0.0,
    0.0,
    0.0,
    0.0,
    0.0,
    0.0,
    0.0,
    0.0,
    0.0,
    0.0,
    0.0,
    0.0,
    0.0,
    0.0,
    0.0,
    0.0,
    0.0,
    0.0,
    0.0,
    0.0,
    0.0,
    0.0,
    0.0,
    0.0,
    0.0,
    0.0,
    0.0,
    0.0,
    0.0,
    0.0,
    0.0,
    0.0,
    0.0,
    0.0,
    0.0,
    0.0,
    0.0,
    0.0,
    0.0,
    0.0,
    0.0,
    0.0,
    0.0,
    0.0,
    0.0,
    0.0
  ],
  "stranded_vehicle_count": 0,
  "total_charging_events": 0,
  "vehicle_charging_events": {},
  "router_execution_times": [
    0.23442380200140178,
    0.26192263000120874,
    0.3099461719975807,
    0.3613374459964689,
    0.2097682449966669,
    0.1902797630027635,
    0.396898727005464,
    0.24973039199539926,
    0.34652710700174794,
    0.3516243519989075,
    0.2908853970002383,
    0.2864103100000648,
    0.24073823299841024,
    0.19307517299603205,
    0.16092268799548037,
    0.21168635699723382,
    0.48080978699726984,
    0.20039730799908284,
    0.2495505580009194,
    0.4451222359930398,
    0.33734096901025623,
    0.13341109700559173,
    0.287676483989344,
    0.7424347859923728,
    0.20076154799608048,
    0.45116674501332454,
    0.5745687680027913,
    0.3722526389901759,
    0.30124844099918846,
    0.7182576550112572,
    0.17220220700255595,
    0.4526455180021003,
    0.23002050700597465,
    0.20435746900329832,
    0.1285602550051408,
    0.3971355709945783,
    0.41941086600127164,
    0.3497820680058794,
    0.4661903319938574,
    0.3475825130008161,
    0.27563933400961105,
    0.32311498699709773,
    0.4676799309963826,
    0.18436353000288364,
    0.20021824099239893,
    0.15171282899973448,
    0.2785098949971143,
    0.44201691199850757,
    0.5397399520006729,
    0.544856680004159,
    0.510286361008184,
    0.5743858100031503,
    0.48590979901200626,
    0.26697464199969545,
    0.3470184109901311,
    0.3334945120004704,
    0.18163753300905228,
    0.32162294699810445,
    0.3296546030032914,
    0.5500175290071638,
    0.2828592189907795,
    0.2432066009932896,
    0.26013747199613135,
    0.2693921199970646,
    0.35753453499637544,
    0.26697988700470887,
    0.22943295699951705,
    0.5348429130099248,
    0.4050791330082575,
    0.353302823001286,
    0.288885116999154,
    0.4602142860094318,
    0.42256491600710433,
    0.4420206130016595,
    0.2770376650005346,
    0.2677022549905814,
    0.2733823040034622,
    0.5846083359938348,
    0.34948964600334875,
    0.2780111269967165,
    0.6907734280102886,
    0.6219786170113366,
    0.3622628459997941,
    0.39495623599214014,
    0.7735054419899825,
    0.6861808190005831,
    0.3872338130022399,
    0.3110607050039107,
    0.3786150960077066,
    0.21118233200104441,
    0.483723972007283,
    0.2701323399960529,
    0.3299548190116184,
    0.39209509300417267,
    0.23708266898756847,
    0.4575073300075019,
    0.17227741099486593,
    0.4161516849999316,
    0.24083897299715318,
    0.43762169100227766,
    0.3692846100020688,
    0.2838761470047757,
    0.3814972630061675,
    0.38434859899280127,
    0.41297686100006104,
    0.39772038299997803,
    0.0626172430056613,
    0.35313743399456143,
    0.23118692201387603,
    0.22777389000111725,
    0.20998639600293245,
    0.26006765199417714,
    0.30211601899645757,
    0.29132479199324735,
    0.43248264299472794,
    0.2971459429973038,
    0.4634255560085876,
    0.45743416500044987,
    0.2964856710023014,
    0.19040403500548564,
    0.38814641399949323,
    0.31127136599388905,
    0.27662933300598525,
    0.4006855689949589,
    0.23148630000650883,
    0.3206549259921303,
    0.24737723599537276,
    0.32482526400417555,
    0.773178575997008,
    0.11766669800272211,
    0.5372917240019888,
    0.3876407939969795,
    0.2816346600011457,
    0.8618522460019449,
    0.2834967890084954,
    0.3188759030017536,
    0.4263678879942745,
    0.2326205800054595,
    0.5332097620121203,
    0.8244896929973038,
    1.1776512739888858,
    0.2726660560001619,
    0.57817368900578,
    0.32489992000046186,
    0.1884007170010591,
    0.49987512099323794,
    0.24966929900983814,
    0.41874869700404815,
    0.017623034000280313,
    0.3060413339990191,
    0.2824260769993998,
    0.2632376630062936,
    0.2074394579976797,
    0.5291590069973608,
    0.4204586010018829,
    0.1985553889971925,
    0.1574925879976945,
    0.1890401069977088,
    0.19455977200414054,
    0.36471665700082667,
    0.25743170399800874,
    0.2902193250047276,
    0.21136558598664124,
    0.5103392519959016,
    0.09437092499865685,
    0.32693534599093255,
    0.3954576760006603,
    0.3648742290097289,
    0.3606963889906183,
    0.353087133000372,
    0.3505277770018438,
    0.3108921509992797,
    0.4645187559945043,
    0.41570353400311433,
    0.1300653409998631,
    0.3045083430042723,
    0.310516807003296,
    0.25245871499646455,
    0.5959541549964342,
    0.3438097369944444,
    0.3497956310020527,
    0.18466329800139647,
    0.47538259900466073,
    0.5347611679899273,
    0.47589382900332566,
    0.3431351319886744,
    0.5487800429982599,
    0.21359748698887415,
    0.551078057003906,
    0.5332836589950603,
    0.34702496499812696,
    0.4830107369925827,
    0.4723540279956069,
    0.307107016997179,
    0.31980751900118776,
    0.6469452790042851,
    0.6458018200064544,
    0.15228553701308556,
    0.5841134389920626,
    0.5371808299969416
  ],
  "router_convergence_speeds": [],
  "adaptation_times_after_disruptions": [],
  "route_stability_metrics": [],
  "subsystem_contributions": [],
  "exploration_ratios": [],
  "vehicles": 200,
  "experiment_metadata": {
    "python_version": "3.12.3 (main, Jun 19 2026, 12:46:00) [GCC 13.3.0]",
    "sumo_version": "Eclipse SUMO sumo 1.27.1",
    "os_info": "Linux-6.17.0-35-generic-x86_64-with-glibc2.39",
    "cpu_info": "x86_64 (4 cores)",
    "random_seed": 1,
    "network_file_path": "data/networks/midtown_manhattan.net.xml",
    "network_sha256": "c2f5702163acf3377f74e03e4bce9598f17aeab54f245edc3daf12de8bf63275",
    "git_commit": "c40f23f73f4d46d41645c27d20c2359d05da2443"
  }
}